Workbook

Sheet Dashboard
A1: Dashboard ejecutivo - Madurez del SGPDP para Empresas del Sector Comercio
A2: Modelo SMARTCIDI | LOPDP Ecuador | 10 dimensiones | evidencia, criticidad, bloqueantes y plan de acción
A4: Madurez global ponderada | B4: =IFERROR(SUMPRODUCT(Dimensiones!B4:B13,Dimensiones!F4:F13)/SUM(Dimensiones!B4:B13),0) -> 0 | D4: Dimensión | E4: Peso | F4: Score | G4: Nivel | H4: Brechas A/C
A5: Cobertura de evaluación | B5: =IFERROR(SUM(Dimensiones!D4:D13)/SUM(Dimensiones!C4:C13),0) -> 0 | D5: =Dimensiones!A4 -> Gobierno y responsabilidad proactiva | E5: =Dimensiones!B4 -> 0.12 | F5: =Dimensiones!F4 -> 0 | G5: =Dimensiones!G4 -> Sin evaluación suficiente | H5: =Dimensiones!H4 -> 0
A6: Nivel teórico numérico | B6: =IF(B4<0.4,1,IF(B4<0.6,2,IF(B4<0.75,3,IF(B4<0.9,4,5)))) -> 1 | D6: =Dimensiones!A5 -> Inventario, RAT, finalidades y legitimación | E6: =Dimensiones!B5 -> 0.14 | F6: =Dimensiones!F5 -> 0 | G6: =Dimensiones!G5 -> Sin evaluación suficiente | H6: =Dimensiones!H5 -> 0
A7: Bloqueantes abiertos | B7: =COUNTIFS(ASSESSMENT!$Q:$Q,"Sí",ASSESSMENT!$M:$M,"<3",ASSESSMENT!$K:$K,">=1") -> 0 | D7: =Dimensiones!A6 -> Transparencia e información al titular | E7: =Dimensiones!B6 -> 0.08 | F7: =Dimensiones!F6 -> 0 | G7: =Dimensiones!G6 -> Sin evaluación suficiente | H7: =Dimensiones!H6 -> 0
A8: Brechas críticas | B8: =COUNTIFS(ASSESSMENT!$P:$P,"Crítico") -> 0 | D8: =Dimensiones!A7 -> Derechos de titulares | E8: =Dimensiones!B7 -> 0.08 | F8: =Dimensiones!F7 -> 0 | G8: =Dimensiones!G7 -> Sin evaluación suficiente | H8: =Dimensiones!H7 -> 0
A9: Brechas altas | B9: =COUNTIFS(ASSESSMENT!$P:$P,"Alto") -> 0 | D9: =Dimensiones!A8 -> Procesos críticos de comercio y ciclo de vida de datos | E9: =Dimensiones!B8 -> 0.1 | F9: =Dimensiones!F8 -> 0 | G9: =Dimensiones!G8 -> Sin evaluación suficiente | H9: =Dimensiones!H8 -> 0
A10: Evidencia insuficiente en controles críticos | B10: =COUNTIFS(ASSESSMENT!$J:$J,">=4",ASSESSMENT!$L:$L,"<2",ASSESSMENT!$I:$I,"Sí",ASSESSMENT!$K:$K,">=1") -> 0 | D10: =Dimensiones!A9 -> Encargados, proveedores y transferencias | E10: =Dimensiones!B9 -> 0.1 | F10: =Dimensiones!F9 -> 0 | G10: =Dimensiones!G9 -> Sin evaluación suficiente | H10: =Dimensiones!H9 -> 0
A11: Nivel final ajustado | B11: =IF(B5<0.6,0,MIN(B6,IF(B7>0,2,5),IF(B10>0,3,5))) -> 0 | D11: =Dimensiones!A10 -> Seguridad de datos personales | E11: =Dimensiones!B10 -> 0.14 | F11: =Dimensiones!F10 -> 0 | G11: =Dimensiones!G10 -> Sin evaluación suficiente | H11: =Dimensiones!H10 -> 0
A12: Resultado ejecutivo | B12: =IF(B11=0,"Sin evaluación suficiente",IF(B11=1,"Nivel 1 - Inicial / Reactivo",IF(B11=2,"Nivel 2 - Básico / Repetible",IF(B11=3,"Nivel 3 - Definido / Documentado",IF(B11=4,"Nivel 4 - Gestionado / Demostrable","Nivel 5 - Optimizado / Mejora continua"))))) -> Sin evaluación suficiente | D12: =Dimensiones!A11 -> Incidentes y vulneraciones | E12: =Dimensiones!B11 -> 0.08 | F12: =Dimensiones!F11 -> 0 | G12: =Dimensiones!G11 -> Sin evaluación suficiente | H12: =Dimensiones!H11 -> 0
D13: =Dimensiones!A12 -> Riesgos, EIPD, LIA y privacidad desde el diseño | E13: =Dimensiones!B12 -> 0.11 | F13: =Dimensiones!F12 -> 0 | G13: =Dimensiones!G12 -> Sin evaluación suficiente | H13: =Dimensiones!H12 -> 0
A14: Antes de aplicar: completar 'Perfil Comercio' y revisar 'Guía Aplicación Comercio'. El resultado final se ajusta por cobertura, evidencia y bloqueantes; no debe interpretarse como certificación legal. | D14: Capacitación, cultura, auditoría y mejora continua | E14: 0.05 | F14: =Dimensiones!F13 -> 0 | G14: =Dimensiones!G13 -> Sin evaluación suficiente | H14: =Dimensiones!H13 -> 0

Sheet ASSESSMENT
A1: Matriz de Madurez del Sistema de Gestión de Protección de Datos Personales - Sector Comercio Ecuador
A2: Versión borrador técnico-consultivo | Aplicable a empresas de comercio minorista, mayorista, e-commerce u omnicanal | Evaluación 1-5 con evidencia
A3: Uso didáctico: completar 'Perfil Comercio' y revisar la hoja 'Guía Aplicación Comercio'. Completar Aplica, Nivel asignado, Nivel evidencia, hallazgos y plan; el modelo calcula madurez, brechas y riesgo.
A4: Metodología resumida | B4: Aplica=Sí entra al cálculo; Aplica=No se excluye. Criticidad pondera el control. Nivel asignado mide madurez observada. Nivel evidencia limita el resultado. Nivel efectivo=MIN(Nivel asignado, Evidencia+1). Riesgo=(5-Nivel efectivo)×Criticidad.
A5: Recomendación de uso | B5: Para una empresa comercial, validar mínimo: clientes y prospectos, tiendas/puntos de venta, POS y facturación, e-commerce si aplica, pagos, CRM/marketing, fidelización, logística/entregas, proveedores, RR. HH., seguridad e incidentes.
A6: ID | B6: Dimensión | C6: Peso Dimensión | D6: Control / Subdimensión | E6: Pregunta de evaluación | F6: Criterio para evaluar madurez | G6: Evidencia solicitada | H6: Responsable / área a entrevistar | I6: Aplica | J6: Criticidad (1-5) | K6: Nivel asignado (1-5) | L6: Nivel evidencia (0-4) | M6: Nivel efectivo | N6: Score ponderado | O6: Base ponderada | P6: Riesgo de brecha | Q6: Bloqueante de madurez | R6: Estado actual / hallazgo | S6: Brecha identificada | T6: Acción recomendada | U6: Prioridad sugerida | V6: Responsable sugerido | W6: Plazo sugerido | X6: Evidencia de cierre | Y6: Estado del plan | Z6: Observaciones
A7: 1 | B7: Gobierno y responsabilidad proactiva | C7: 0.12 | D7: Política de protección de datos personales para la empresa | E7: ¿Existe una política interna de protección de datos personales aprobada, comunicada y adaptada a la operación comercial de la empresa? | F7: La política está aprobada, vigente, asigna roles y contempla clientes, prospectos, colaboradores, proveedores, puntos de venta, canales digitales, CRM, e-commerce si aplica y se revisa periódicamente. | G7: Política aprobada, acta de aprobación, control de versión, evidencia de comunicación interna. | H7: Gerencia / Cumplimiento / DPO | I7: Sí | J7: 5 | M7: =IF(I7="No","N/A",IF(OR(K7="",L7=""),"",MIN(K7,L7+1))) | N7: =IF(OR(I7="No",M7="",M7="N/A"),0,(M7/5)*J7) -> 0 | O7: =IF(I7="Sí",J7,0) -> 5 | P7: =IF(I7="No","No aplica",IF(M7="","Pendiente",IF((5-M7)*J7>=15,"Crítico",IF((5-M7)*J7>=9,"Alto",IF((5-M7)*J7>=5,"Medio","Bajo"))))) -> Pendiente | Q7: Sí | T7: Aprobar o actualizar la política interna, comunicarla formalmente y definir revisión anual. | U7: =IF(P7="Crítico","Crítica",IF(P7="Alto","Alta",IF(P7="Medio","Media",IF(P7="Bajo","Baja","Pendiente")))) -> Pendiente | W7: =IF(U7="Crítica","30 días",IF(U7="Alta","60 días",IF(U7="Media","90 días",IF(U7="Baja","180 días","Por definir")))) -> Por definir | Y7: Pendiente
A8: 2 | B8: Gobierno y responsabilidad proactiva | C8: 0.12 | D8: Roles, responsabilidades y sponsor ejecutivo | E8: ¿Están definidos los responsables internos de protección de datos por área/proceso? | F8: Existen responsables, sponsor ejecutivo y responsabilidades documentadas para procesos críticos. | G8: Matriz RACI, actas de designación, organigrama, perfiles de responsabilidad. | H8: Gerencia / Talento Humano / DPO | I8: Sí | J8: 5 | M8: =IF(I8="No","N/A",IF(OR(K8="",L8=""),"",MIN(K8,L8+1))) | N8: =IF(OR(I8="No",M8="",M8="N/A"),0,(M8/5)*J8) -> 0 | O8: =IF(I8="Sí",J8,0) -> 5 | P8: =IF(I8="No","No aplica",IF(M8="","Pendiente",IF((5-M8)*J8>=15,"Crítico",IF((5-M8)*J8>=9,"Alto",IF((5-M8)*J8>=5,"Medio","Bajo"))))) -> Pendiente | Q8: Sí | T8: Definir responsables internos por proceso y formalizar su rol con soporte de gerencia. | U8: =IF(P8="Crítico","Crítica",IF(P8="Alto","Alta",IF(P8="Medio","Media",IF(P8="Bajo","Baja","Pendiente")))) -> Pendiente | W8: =IF(U8="Crítica","30 días",IF(U8="Alta","60 días",IF(U8="Media","90 días",IF(U8="Baja","180 días","Por definir")))) -> Por definir | Y8: Pendiente
A9: 3 | B9: Gobierno y responsabilidad proactiva | C9: 0.12 | D9: Evaluación de aplicabilidad y designación del DPD | E9: ¿La empresa ha evaluado y documentado si está obligada a designar Delegado de Protección de Datos y, cuando corresponde, la designación está formalizada? | F9: Existe análisis documentado de aplicabilidad; si corresponde designación, el DPD está formalmente nombrado, registrado y cuenta con canal de contacto y acceso a dirección. | G9: Análisis de aplicabilidad, nombramiento/registro si corresponde, contrato o alcance, canal de contacto, informes del DPD. | H9: Gerencia / Legal / Privacidad | I9: Sí | J9: 4 | M9: =IF(I9="No","N/A",IF(OR(K9="",L9=""),"",MIN(K9,L9+1))) | N9: =IF(OR(I9="No",M9="",M9="N/A"),0,(M9/5)*J9) -> 0 | O9: =IF(I9="Sí",J9,0) -> 4 | P9: =IF(I9="No","No aplica",IF(M9="","Pendiente",IF((5-M9)*J9>=15,"Crítico",IF((5-M9)*J9>=9,"Alto",IF((5-M9)*J9>=5,"Medio","Bajo"))))) -> Pendiente | Q9: No | T9: Documentar la evaluación de aplicabilidad del DPD y, si corresponde, formalizar nombramiento, registro, canal y alcance. | U9: =IF(P9="Crítico","Crítica",IF(P9="Alto","Alta",IF(P9="Medio","Media",IF(P9="Bajo","Baja","Pendiente")))) -> Pendiente | W9: =IF(U9="Crítica","30 días",IF(U9="Alta","60 días",IF(U9="Media","90 días",IF(U9="Baja","180 días","Por definir")))) -> Por definir | Y9: Pendiente
A10: 4 | B10: Gobierno y responsabilidad proactiva | C10: 0.12 | D10: Independencia, recursos y seguimiento del DPD cuando aplique | E10: ¿Cuando existe DPD, la empresa garantiza independencia, acceso a dirección, recursos y evidencia de seguimiento de sus recomendaciones? | F10: La función mantiene independencia y segregación respecto de decisiones sobre fines y medios del tratamiento; existe acceso a alta dirección y trazabilidad de recomendaciones. | G10: Actas, agenda, matriz de recomendaciones, reportes de seguimiento, evidencia de escalamiento. | H10: Gerencia / DPD / Legal / Áreas | I10: Sí | J10: 4 | M10: =IF(I10="No","N/A",IF(OR(K10="",L10=""),"",MIN(K10,L10+1))) | N10: =IF(OR(I10="No",M10="",M10="N/A"),0,(M10/5)*J10) -> 0 | O10: =IF(I10="Sí",J10,0) -> 4 | P10: =IF(I10="No","No aplica",IF(M10="","Pendiente",IF((5-M10)*J10>=15,"Crítico",IF((5-M10)*J10>=9,"Alto",IF((5-M10)*J10>=5,"Medio","Bajo"))))) -> Pendiente | Q10: No | T10: Formalizar independencia, línea de reporte, recursos y seguimiento de recomendaciones del DPD cuando aplique. | U10: =IF(P10="Crítico","Crítica",IF(P10="Alto","Alta",IF(P10="Medio","Media",IF(P10="Bajo","Baja","Pendiente")))) -> Pendiente | W10: =IF(U10="Crítica","30 días",IF(U10="Alta","60 días",IF(U10="Media","90 días",IF(U10="Baja","180 días","Por definir")))) -> Por definir | Y10: Pendiente
A11: 5 | B11: Gobierno y responsabilidad proactiva | C11: 0.12 | D11: Mapa de obligaciones y base normativa aplicable | E11: ¿La organización tiene identificadas las obligaciones LOPDP aplicables a su operación? | F11: Existe un mapa normativo que vincula obligaciones con procesos, controles y evidencias. | G11: Mapa normativo, matriz de cumplimiento, criterios de aplicabilidad, revisión legal-consultiva. | H11: Cumplimiento / Legal / DPO | I11: Sí | J11: 4 | M11: =IF(I11="No","N/A",IF(OR(K11="",L11=""),"",MIN(K11,L11+1))) | N11: =IF(OR(I11="No",M11="",M11="N/A"),0,(M11/5)*J11) -> 0 | O11: =IF(I11="Sí",J11,0) -> 4 | P11: =IF(I11="No","No aplica",IF(M11="","Pendiente",IF((5-M11)*J11>=15,"Crítico",IF((5-M11)*J11>=9,"Alto",IF((5-M11)*J11>=5,"Medio","Bajo"))))) -> Pendiente | Q11: No | T11: Elaborar matriz de obligaciones aplicables y vincularlas con controles internos. | U11: =IF(P11="Crítico","Crítica",IF(P11="Alto","Alta",IF(P11="Medio","Media",IF(P11="Bajo","Baja","Pendiente")))) -> Pendiente | W11: =IF(U11="Crítica","30 días",IF(U11="Alta","60 días",IF(U11="Media","90 días",IF(U11="Baja","180 días","Por definir")))) -> Por definir | Y11: Pendiente
A12: 6 | B12: Gobierno y responsabilidad proactiva | C12: 0.12 | D12: Presupuesto y recursos | E12: ¿Existe asignación de recursos para sostener el sistema de protección de datos? | F12: Se asignan recursos para capacitación, herramientas, seguridad, consultoría, auditoría y mejoras. | G12: Presupuesto, plan anual, aprobaciones, órdenes de compra, cronograma. | H12: Gerencia / Finanzas / TI | I12: Sí | J12: 3 | M12: =IF(I12="No","N/A",IF(OR(K12="",L12=""),"",MIN(K12,L12+1))) | N12: =IF(OR(I12="No",M12="",M12="N/A"),0,(M12/5)*J12) -> 0 | O12: =IF(I12="Sí",J12,0) -> 3 | P12: =IF(I12="No","No aplica",IF(M12="","Pendiente",IF((5-M12)*J12>=15,"Crítico",IF((5-M12)*J12>=9,"Alto",IF((5-M12)*J12>=5,"Medio","Bajo"))))) -> Pendiente | Q12: No | T12: Definir presupuesto proporcional al riesgo para sostener cumplimiento y seguridad. | U12: =IF(P12="Crítico","Crítica",IF(P12="Alto","Alta",IF(P12="Medio","Media",IF(P12="Bajo","Baja","Pendiente")))) -> Pendiente | W12: =IF(U12="Crítica","30 días",IF(U12="Alta","60 días",IF(U12="Media","90 días",IF(U12="Baja","180 días","Por definir")))) -> Por definir | Y12: Pendiente
A13: 7 | B13: Gobierno y responsabilidad proactiva | C13: 0.12 | D13: Gestión documental del SGPDP | E13: ¿Los documentos de protección de datos tienen control de versión, dueño y fecha de revisión? | F13: Documentos controlados, aprobados, versionados y disponibles para responsables internos. | G13: Repositorio, control maestro de documentos, versiones, responsables, historial de cambios. | H13: Cumplimiento / Calidad / DPO | I13: Sí | J13: 3 | M13: =IF(I13="No","N/A",IF(OR(K13="",L13=""),"",MIN(K13,L13+1))) | N13: =IF(OR(I13="No",M13="",M13="N/A"),0,(M13/5)*J13) -> 0 | O13: =IF(I13="Sí",J13,0) -> 3 | P13: =IF(I13="No","No aplica",IF(M13="","Pendiente",IF((5-M13)*J13>=15,"Crítico",IF((5-M13)*J13>=9,"Alto",IF((5-M13)*J13>=5,"Medio","Bajo"))))) -> Pendiente | Q13: No | T13: Crear control maestro documental para políticas, matrices, procedimientos y evidencias. | U13: =IF(P13="Crítico","Crítica",IF(P13="Alto","Alta",IF(P13="Medio","Media",IF(P13="Bajo","Baja","Pendiente")))) -> Pendiente | W13: =IF(U13="Crítica","30 días",IF(U13="Alta","60 días",IF(U13="Media","90 días",IF(U13="Baja","180 días","Por definir")))) -> Por definir | Y13: Pendiente
A14: 8 | B14: Gobierno y responsabilidad proactiva | C14: 0.12 | D14: Indicadores y reportes a dirección | E14: ¿Se reportan indicadores de protección de datos a la alta dirección? | F14: Existen KPIs de incidentes, derechos, capacitación, riesgos, proveedores y avance de acciones. | G14: Dashboard, informes mensuales/trimestrales, actas de revisión por dirección. | H14: DPO / Gerencia / Cumplimiento | I14: Sí | J14: 3 | M14: =IF(I14="No","N/A",IF(OR(K14="",L14=""),"",MIN(K14,L14+1))) | N14: =IF(OR(I14="No",M14="",M14="N/A"),0,(M14/5)*J14) -> 0 | O14: =IF(I14="Sí",J14,0) -> 3 | P14: =IF(I14="No","No aplica",IF(M14="","Pendiente",IF((5-M14)*J14>=15,"Crítico",IF((5-M14)*J14>=9,"Alto",IF((5-M14)*J14>=5,"Medio","Bajo"))))) -> Pendiente | Q14: No | T14: Definir indicadores mínimos y reportarlos periódicamente a dirección. | U14: =IF(P14="Crítico","Crítica",IF(P14="Alto","Alta",IF(P14="Medio","Media",IF(P14="Bajo","Baja","Pendiente")))) -> Pendiente | W14: =IF(U14="Crítica","30 días",IF(U14="Alta","60 días",IF(U14="Media","90 días",IF(U14="Baja","180 días","Por definir")))) -> Por definir | Y14: Pendiente
A15: 9 | B15: Inventario, RAT, finalidades y legitimación | C15: 0.14 | D15: Inventario de tratamientos de la empresa | E15: ¿Existe un inventario actualizado de tratamientos de datos personales por proceso comercial y corporativo? | F15: El inventario identifica captación y registro de clientes, ventas/POS, facturación, e-commerce si aplica, pagos, marketing/CRM, servicio al cliente, logística, RR. HH., proveedores y seguridad. | G15: Inventario de datos, mapa de procesos, fichas de tratamiento. | H15: DPO / Procesos / Áreas | I15: Sí | J15: 5 | M15: =IF(I15="No","N/A",IF(OR(K15="",L15=""),"",MIN(K15,L15+1))) | N15: =IF(OR(I15="No",M15="",M15="N/A"),0,(M15/5)*J15) -> 0 | O15: =IF(I15="Sí",J15,0) -> 5 | P15: =IF(I15="No","No aplica",IF(M15="","Pendiente",IF((5-M15)*J15>=15,"Crítico",IF((5-M15)*J15>=9,"Alto",IF((5-M15)*J15>=5,"Medio","Bajo"))))) -> Pendiente | Q15: Sí | T15: Levantar o actualizar inventario de tratamientos con dueños por proceso. | U15: =IF(P15="Crítico","Crítica",IF(P15="Alto","Alta",IF(P15="Medio","Media",IF(P15="Bajo","Baja","Pendiente")))) -> Pendiente | W15: =IF(U15="Crítica","30 días",IF(U15="Alta","60 días",IF(U15="Media","90 días",IF(U15="Baja","180 días","Por definir")))) -> Por definir | Y15: Pendiente
A16: 10 | B16: Inventario, RAT, finalidades y legitimación | C16: 0.14 | D16: Registro de Actividades de Tratamiento (RAT) | E16: ¿Existe un RAT actualizado y alineado con los procesos reales de la empresa? | F16: El RAT contiene actividades, finalidades, categorías de titulares, datos, destinatarios, conservación, medidas de seguridad, encargados y transferencias cuando correspondan. | G16: RAT, control de cambios, evidencia de validación por áreas. | H16: DPO / Cumplimiento / Áreas | I16: Sí | J16: 5 | M16: =IF(I16="No","N/A",IF(OR(K16="",L16=""),"",MIN(K16,L16+1))) | N16: =IF(OR(I16="No",M16="",M16="N/A"),0,(M16/5)*J16) -> 0 | O16: =IF(I16="Sí",J16,0) -> 5 | P16: =IF(I16="No","No aplica",IF(M16="","Pendiente",IF((5-M16)*J16>=15,"Crítico",IF((5-M16)*J16>=9,"Alto",IF((5-M16)*J16>=5,"Medio","Bajo"))))) -> Pendiente | Q16: Sí | T16: Construir o actualizar RAT con base en procesos reales y evidencia de validación. | U16: =IF(P16="Crítico","Crítica",IF(P16="Alto","Alta",IF(P16="Medio","Media",IF(P16="Bajo","Baja","Pendiente")))) -> Pendiente | W16: =IF(U16="Crítica","30 días",IF(U16="Alta","60 días",IF(U16="Media","90 días",IF(U16="Baja","180 días","Por definir")))) -> Por definir | Y16: Pendiente
A17: 11 | B17: Inventario, RAT, finalidades y legitimación | C17: 0.14 | D17: Finalidades específicas y documentadas | E17: ¿Cada tratamiento tiene finalidades claras, específicas y documentadas? | F17: Las finalidades son explícitas, legítimas, no genéricas y se reflejan en avisos y procesos. | G17: RAT, avisos de privacidad, formularios, procedimientos, bases de legitimación. | H17: DPO / Legal / Áreas | I17: Sí | J17: 5 | M17: =IF(I17="No","N/A",IF(OR(K17="",L17=""),"",MIN(K17,L17+1))) | N17: =IF(OR(I17="No",M17="",M17="N/A"),0,(M17/5)*J17) -> 0 | O17: =IF(I17="Sí",J17,0) -> 5 | P17: =IF(I17="No","No aplica",IF(M17="","Pendiente",IF((5-M17)*J17>=15,"Crítico",IF((5-M17)*J17>=9,"Alto",IF((5-M17)*J17>=5,"Medio","Bajo"))))) -> Pendiente | Q17: Sí | T17: Depurar finalidades y eliminar descripciones genéricas o incompatibles. | U17: =IF(P17="Crítico","Crítica",IF(P17="Alto","Alta",IF(P17="Medio","Media",IF(P17="Bajo","Baja","Pendiente")))) -> Pendiente | W17: =IF(U17="Crítica","30 días",IF(U17="Alta","60 días",IF(U17="Media","90 días",IF(U17="Baja","180 días","Por definir")))) -> Por definir | Y17: Pendiente
A18: 12 | B18: Inventario, RAT, finalidades y legitimación | C18: 0.14 | D18: Base de legitimación por tratamiento | E18: ¿Cada tratamiento tiene identificada y justificada su base de legitimación? | F18: La base se asigna por tratamiento, con racionales y criterios de aplicabilidad. | G18: Matriz de bases, consentimientos, contratos, obligación legal, LIA cuando aplique. | H18: DPO / Legal / Áreas | I18: Sí | J18: 5 | M18: =IF(I18="No","N/A",IF(OR(K18="",L18=""),"",MIN(K18,L18+1))) | N18: =IF(OR(I18="No",M18="",M18="N/A"),0,(M18/5)*J18) -> 0 | O18: =IF(I18="Sí",J18,0) -> 5 | P18: =IF(I18="No","No aplica",IF(M18="","Pendiente",IF((5-M18)*J18>=15,"Crítico",IF((5-M18)*J18>=9,"Alto",IF((5-M18)*J18>=5,"Medio","Bajo"))))) -> Pendiente | Q18: Sí | T18: Validar bases de legitimación por proceso y documentar rationale. | U18: =IF(P18="Crítico","Crítica",IF(P18="Alto","Alta",IF(P18="Medio","Media",IF(P18="Bajo","Baja","Pendiente")))) -> Pendiente | W18: =IF(U18="Crítica","30 días",IF(U18="Alta","60 días",IF(U18="Media","90 días",IF(U18="Baja","180 días","Por definir")))) -> Por definir | Y18: Pendiente
... A86: 80 | B86: Capacitación, cultura, auditoría y mejora continua | C86: 0.05 | D86: Mejora continua y revisión por dirección | E86: ¿La alta dirección revisa periódicamente resultados, riesgos y madurez del SGPDP? | F86: Se presentan indicadores, brechas, riesgos residuales y decisiones de mejora. | G86: Informe anual/semestral, actas, hoja de ruta, KPIs. | H86: Gerencia / DPO / Cumplimiento | I86: Sí | J86: 4 | M86: =IF(I86="No","N/A",IF(OR(K86="",L86=""),"",MIN(K86,L86+1))) | N86: =IF(OR(I86="No",M86="",M86="N/A"),0,(M86/5)*J86) -> 0 | O86: =IF(I86="Sí",J86,0) -> 4 | P86: =IF(I86="No","No aplica",IF(M86="","Pendiente",IF((5-M86)*J86>=15,"Crítico",IF((5-M86)*J86>=9,"Alto",IF((5-M86)*J86>=5,"Medio","Bajo"))))) -> Pendiente | Q86: No | T86: Establecer revisión por dirección y hoja de ruta anual. | U86: =IF(P86="Crítico","Crítica",IF(P86="Alto","Alta",IF(P86="Medio","Media",IF(P86="Bajo","Baja","Pendiente")))) -> Pendiente | W86: =IF(U86="Crítica","30 días",IF(U86="Alta","60 días",IF(U86="Media","90 días",IF(U86="Baja","180 días","Por definir")))) -> Por definir | Y86: Pendiente

Sheet Dimensiones
A1: Resultados por dimensión del SGPDP
A3: Dimensión | B3: Peso | C3: Ítems aplicables | D3: Ítems evaluados | E3: % cobertura | F3: Score dimensión | G3: Nivel dimensión | H3: Brechas críticas/altas | I3: Observación automática
A4: Gobierno y responsabilidad proactiva | B4: 0.12 | C4: =COUNTIFS(ASSESSMENT!$B:$B,A4,ASSESSMENT!$I:$I,"Sí") -> 8 | D4: =COUNTIFS(ASSESSMENT!$B:$B,A4,ASSESSMENT!$I:$I,"Sí",ASSESSMENT!$K:$K,">=1") -> 0 | E4: =IFERROR(D4/C4,0) -> 0 | F4: =IFERROR(SUMIFS(ASSESSMENT!$N:$N,ASSESSMENT!$B:$B,A4)/SUMIFS(ASSESSMENT!$O:$O,ASSESSMENT!$B:$B,A4),0) -> 0 | G4: =IF(E4<0.6,"Sin evaluación suficiente",IF(F4<0.4,"Nivel 1 - Inicial",IF(F4<0.6,"Nivel 2 - Básico",IF(F4<0.75,"Nivel 3 - Definido",IF(F4<0.9,"Nivel 4 - Gestionado","Nivel 5 - Optimizado"))))) -> Sin evaluación suficiente | H4: =COUNTIFS(ASSESSMENT!$B:$B,A4,ASSESSMENT!$P:$P,"Crítico")+COUNTIFS(ASSESSMENT!$B:$B,A4,ASSESSMENT!$P:$P,"Alto") -> 0 | I4: =IF(E4<0.6,"Completar evaluación",IF(H4>0,"Cerrar brechas prioritarias","Mantener y mejorar")) -> Completar evaluación
A5: Inventario, RAT, finalidades y legitimación | B5: 0.14 | C5: =COUNTIFS(ASSESSMENT!$B:$B,A5,ASSESSMENT!$I:$I,"Sí") -> 8 | D5: =COUNTIFS(ASSESSMENT!$B:$B,A5,ASSESSMENT!$I:$I,"Sí",ASSESSMENT!$K:$K,">=1") -> 0 | E5: =IFERROR(D5/C5,0) -> 0 | F5: =IFERROR(SUMIFS(ASSESSMENT!$N:$N,ASSESSMENT!$B:$B,A5)/SUMIFS(ASSESSMENT!$O:$O,ASSESSMENT!$B:$B,A5),0) -> 0 | G5: =IF(E5<0.6,"Sin evaluación suficiente",IF(F5<0.4,"Nivel 1 - Inicial",IF(F5<0.6,"Nivel 2 - Básico",IF(F5<0.75,"Nivel 3 - Definido",IF(F5<0.9,"Nivel 4 - Gestionado","Nivel 5 - Optimizado"))))) -> Sin evaluación suficiente | H5: =COUNTIFS(ASSESSMENT!$B:$B,A5,ASSESSMENT!$P:$P,"Crítico")+COUNTIFS(ASSESSMENT!$B:$B,A5,ASSESSMENT!$P:$P,"Alto") -> 0 | I5: =IF(E5<0.6,"Completar evaluación",IF(H5>0,"Cerrar brechas prioritarias","Mantener y mejorar")) -> Completar evaluación
A6: Transparencia e información al titular | B6: 0.08 | C6: =COUNTIFS(ASSESSMENT!$B:$B,A6,ASSESSMENT!$I:$I,"Sí") -> 8 | D6: =COUNTIFS(ASSESSMENT!$B:$B,A6,ASSESSMENT!$I:$I,"Sí",ASSESSMENT!$K:$K,">=1") -> 0 | E6: =IFERROR(D6/C6,0) -> 0 | F6: =IFERROR(SUMIFS(ASSESSMENT!$N:$N,ASSESSMENT!$B:$B,A6)/SUMIFS(ASSESSMENT!$O:$O,ASSESSMENT!$B:$B,A6),0) -> 0 | G6: =IF(E6<0.6,"Sin evaluación suficiente",IF(F6<0.4,"Nivel 1 - Inicial",IF(F6<0.6,"Nivel 2 - Básico",IF(F6<0.75,"Nivel 3 - Definido",IF(F6<0.9,"Nivel 4 - Gestionado","Nivel 5 - Optimizado"))))) -> Sin evaluación suficiente | H6: =COUNTIFS(ASSESSMENT!$B:$B,A6,ASSESSMENT!$P:$P,"Crítico")+COUNTIFS(ASSESSMENT!$B:$B,A6,ASSESSMENT!$P:$P,"Alto") -> 0 | I6: =IF(E6<0.6,"Completar evaluación",IF(H6>0,"Cerrar brechas prioritarias","Mantener y mejorar")) -> Completar evaluación
A7: Derechos de titulares | B7: 0.08 | C7: =COUNTIFS(ASSESSMENT!$B:$B,A7,ASSESSMENT!$I:$I,"Sí") -> 8 | D7: =COUNTIFS(ASSESSMENT!$B:$B,A7,ASSESSMENT!$I:$I,"Sí",ASSESSMENT!$K:$K,">=1") -> 0 | E7: =IFERROR(D7/C7,0) -> 0 | F7: =IFERROR(SUMIFS(ASSESSMENT!$N:$N,ASSESSMENT!$B:$B,A7)/SUMIFS(ASSESSMENT!$O:$O,ASSESSMENT!$B:$B,A7),0) -> 0 | G7: =IF(E7<0.6,"Sin evaluación suficiente",IF(F7<0.4,"Nivel 1 - Inicial",IF(F7<0.6,"Nivel 2 - Básico",IF(F7<0.75,"Nivel 3 - Definido",IF(F7<0.9,"Nivel 4 - Gestionado","Nivel 5 - Optimizado"))))) -> Sin evaluación suficiente | H7: =COUNTIFS(ASSESSMENT!$B:$B,A7,ASSESSMENT!$P:$P,"Crítico")+COUNTIFS(ASSESSMENT!$B:$B,A7,ASSESSMENT!$P:$P,"Alto") -> 0 | I7: =IF(E7<0.6,"Completar evaluación",IF(H7>0,"Cerrar brechas prioritarias","Mantener y mejorar")) -> Completar evaluación
A8: Procesos críticos de comercio y ciclo de vida de datos | B8: 0.1 | C8: =COUNTIFS(ASSESSMENT!$B:$B,A8,ASSESSMENT!$I:$I,"Sí") -> 8 | D8: =COUNTIFS(ASSESSMENT!$B:$B,A8,ASSESSMENT!$I:$I,"Sí",ASSESSMENT!$K:$K,">=1") -> 0 | E8: =IFERROR(D8/C8,0) -> 0 | F8: =IFERROR(SUMIFS(ASSESSMENT!$N:$N,ASSESSMENT!$B:$B,A8)/SUMIFS(ASSESSMENT!$O:$O,ASSESSMENT!$B:$B,A8),0) -> 0 | G8: =IF(E8<0.6,"Sin evaluación suficiente",IF(F8<0.4,"Nivel 1 - Inicial",IF(F8<0.6,"Nivel 2 - Básico",IF(F8<0.75,"Nivel 3 - Definido",IF(F8<0.9,"Nivel 4 - Gestionado","Nivel 5 - Optimizado"))))) -> Sin evaluación suficiente | H8: =COUNTIFS(ASSESSMENT!$B:$B,A8,ASSESSMENT!$P:$P,"Crítico")+COUNTIFS(ASSESSMENT!$B:$B,A8,ASSESSMENT!$P:$P,"Alto") -> 0 | I8: =IF(E8<0.6,"Completar evaluación",IF(H8>0,"Cerrar brechas prioritarias","Mantener y mejorar")) -> Completar evaluación
A9: Encargados, proveedores y transferencias | B9: 0.1 | C9: =COUNTIFS(ASSESSMENT!$B:$B,A9,ASSESSMENT!$I:$I,"Sí") -> 8 | D9: =COUNTIFS(ASSESSMENT!$B:$B,A9,ASSESSMENT!$I:$I,"Sí",ASSESSMENT!$K:$K,">=1") -> 0 | E9: =IFERROR(D9/C9,0) -> 0 | F9: =IFERROR(SUMIFS(ASSESSMENT!$N:$N,ASSESSMENT!$B:$B,A9)/SUMIFS(ASSESSMENT!$O:$O,ASSESSMENT!$B:$B,A9),0) -> 0 | G9: =IF(E9<0.6,"Sin evaluación suficiente",IF(F9<0.4,"Nivel 1 - Inicial",IF(F9<0.6,"Nivel 2 - Básico",IF(F9<0.75,"Nivel 3 - Definido",IF(F9<0.9,"Nivel 4 - Gestionado","Nivel 5 - Optimizado"))))) -> Sin evaluación suficiente | H9: =COUNTIFS(ASSESSMENT!$B:$B,A9,ASSESSMENT!$P:$P,"Crítico")+COUNTIFS(ASSESSMENT!$B:$B,A9,ASSESSMENT!$P:$P,"Alto") -> 0 | I9: =IF(E9<0.6,"Completar evaluación",IF(H9>0,"Cerrar brechas prioritarias","Mantener y mejorar")) -> Completar evaluación
A10: Seguridad de datos personales | B10: 0.14 | C10: =COUNTIFS(ASSESSMENT!$B:$B,A10,ASSESSMENT!$I:$I,"Sí") -> 8 | D10: =COUNTIFS(ASSESSMENT!$B:$B,A10,ASSESSMENT!$I:$I,"Sí",ASSESSMENT!$K:$K,">=1") -> 0 | E10: =IFERROR(D10/C10,0) -> 0 | F10: =IFERROR(SUMIFS(ASSESSMENT!$N:$N,ASSESSMENT!$B:$B,A10)/SUMIFS(ASSESSMENT!$O:$O,ASSESSMENT!$B:$B,A10),0) -> 0 | G10: =IF(E10<0.6,"Sin evaluación suficiente",IF(F10<0.4,"Nivel 1 - Inicial",IF(F10<0.6,"Nivel 2 - Básico",IF(F10<0.75,"Nivel 3 - Definido",IF(F10<0.9,"Nivel 4 - Gestionado","Nivel 5 - Optimizado"))))) -> Sin evaluación suficiente | H10: =COUNTIFS(ASSESSMENT!$B:$B,A10,ASSESSMENT!$P:$P,"Crítico")+COUNTIFS(ASSESSMENT!$B:$B,A10,ASSESSMENT!$P:$P,"Alto") -> 0 | I10: =IF(E10<0.6,"Completar evaluación",IF(H10>0,"Cerrar brechas prioritarias","Mantener y mejorar")) -> Completar evaluación
A11: Incidentes y vulneraciones | B11: 0.08 | C11: =COUNTIFS(ASSESSMENT!$B:$B,A11,ASSESSMENT!$I:$I,"Sí") -> 8 | D11: =COUNTIFS(ASSESSMENT!$B:$B,A11,ASSESSMENT!$I:$I,"Sí",ASSESSMENT!$K:$K,">=1") -> 0 | E11: =IFERROR(D11/C11,0) -> 0 | F11: =IFERROR(SUMIFS(ASSESSMENT!$N:$N,ASSESSMENT!$B:$B,A11)/SUMIFS(ASSESSMENT!$O:$O,ASSESSMENT!$B:$B,A11),0) -> 0 | G11: =IF(E11<0.6,"Sin evaluación suficiente",IF(F11<0.4,"Nivel 1 - Inicial",IF(F11<0.6,"Nivel 2 - Básico",IF(F11<0.75,"Nivel 3 - Definido",IF(F11<0.9,"Nivel 4 - Gestionado","Nivel 5 - Optimizado"))))) -> Sin evaluación suficiente | H11: =COUNTIFS(ASSESSMENT!$B:$B,A11,ASSESSMENT!$P:$P,"Crítico")+COUNTIFS(ASSESSMENT!$B:$B,A11,ASSESSMENT!$P:$P,"Alto") -> 0 | I11: =IF(E11<0.6,"Completar evaluación",IF(H11>0,"Cerrar brechas prioritarias","Mantener y mejorar")) -> Completar evaluación
A12: Riesgos, EIPD, LIA y privacidad desde el diseño | B12: 0.11 | C12: =COUNTIFS(ASSESSMENT!$B:$B,A12,ASSESSMENT!$I:$I,"Sí") -> 8 | D12: =COUNTIFS(ASSESSMENT!$B:$B,A12,ASSESSMENT!$I:$I,"Sí",ASSESSMENT!$K:$K,">=1") -> 0 | E12: =IFERROR(D12/C12,0) -> 0 | F12: =IFERROR(SUMIFS(ASSESSMENT!$N:$N,ASSESSMENT!$B:$B,A12)/SUMIFS(ASSESSMENT!$O:$O,ASSESSMENT!$B:$B,A12),0) -> 0 | G12: =IF(E12<0.6,"Sin evaluación suficiente",IF(F12<0.4,"Nivel 1 - Inicial",IF(F12<0.6,"Nivel 2 - Básico",IF(F12<0.75,"Nivel 3 - Definido",IF(F12<0.9,"Nivel 4 - Gestionado","Nivel 5 - Optimizado"))))) -> Sin evaluación suficiente | H12: =COUNTIFS(ASSESSMENT!$B:$B,A12,ASSESSMENT!$P:$P,"Crítico")+COUNTIFS(ASSESSMENT!$B:$B,A12,ASSESSMENT!$P:$P,"Alto") -> 0 | I12: =IF(E12<0.6,"Completar evaluación",IF(H12>0,"Cerrar brechas prioritarias","Mantener y mejorar")) -> Completar evaluación
A13: Capacitación, cultura, auditoría y mejora continua | B13: 0.05 | C13: =COUNTIFS(ASSESSMENT!$B:$B,A13,ASSESSMENT!$I:$I,"Sí") -> 8 | D13: =COUNTIFS(ASSESSMENT!$B:$B,A13,ASSESSMENT!$I:$I,"Sí",ASSESSMENT!$K:$K,">=1") -> 0 | E13: =IFERROR(D13/C13,0) -> 0 | F13: =IFERROR(SUMIFS(ASSESSMENT!$N:$N,ASSESSMENT!$B:$B,A13)/SUMIFS(ASSESSMENT!$O:$O,ASSESSMENT!$B:$B,A13),0) -> 0 | G13: =IF(E13<0.6,"Sin evaluación suficiente",IF(F13<0.4,"Nivel 1 - Inicial",IF(F13<0.6,"Nivel 2 - Básico",IF(F13<0.75,"Nivel 3 - Definido",IF(F13<0.9,"Nivel 4 - Gestionado","Nivel 5 - Optimizado"))))) -> Sin evaluación suficiente | H13: =COUNTIFS(ASSESSMENT!$B:$B,A13,ASSESSMENT!$P:$P,"Crítico")+COUNTIFS(ASSESSMENT!$B:$B,A13,ASSESSMENT!$P:$P,"Alto") -> 0 | I13: =IF(E13<0.6,"Completar evaluación",IF(H13>0,"Cerrar brechas prioritarias","Mantener y mejorar")) -> Completar evaluación

Sheet Niveles de Madurez
A1: Criterios de madurez del SGPDP
A3: Nivel | B3: Nombre | C3: Criterio operativo | D3: Evidencia típica | E3: Qué demuestra | F3: Rango global
A4: 1 | B4: Inicial / Reactivo | C4: No existe o se gestiona informalmente; depende de personas y no de un sistema. | D4: Entrevista verbal, prácticas no documentadas. | E4: Baja capacidad de demostrar cumplimiento. | F4: 0% - 39%
A5: 2 | B5: Básico / Repetible | C5: Existen prácticas aisladas o documentos iniciales, pero no están integrados ni son uniformes. | D5: Documentos parciales, formatos iniciales, acciones puntuales. | E5: Cumplimiento incipiente con brechas estructurales. | F5: 40% - 59%
A6: 3 | B6: Definido / Documentado | C6: Existen políticas, matrices, procedimientos y responsables definidos. | D6: Documentos aprobados, matrices, registros parciales. | E6: Base de cumplimiento organizada pero con evidencia operativa limitada. | F6: 60% - 74%
A7: 4 | B7: Gestionado / Demostrable | C7: El sistema se aplica, se revisa, tiene seguimiento, métricas y evidencias periódicas. | D7: Registros, actas, indicadores, auditorías internas, seguimiento de brechas. | E7: Cumplimiento operativo y demostrable. | F7: 75% - 89%
A8: 5 | B8: Optimizado / Mejora continua | C8: El sistema está integrado a gobierno, riesgos, seguridad, proveedores, proyectos y mejora continua. | D8: KPIs, revisión por dirección, DPO activo, auditorías, simulacros, mejoras recurrentes. | E8: Madurez avanzada y resiliente. | F8: 90% - 100%

Sheet Plan de Acción
A1: Plan de acción derivado de la Matriz SGPDP
A2: Use filtros para priorizar Crítico/Alto y estados Pendiente/En progreso. Esta hoja replica los ítems evaluados para seguimiento.
A4: ID | B4: Dimensión | C4: Control | D4: Riesgo | E4: Prioridad | F4: Acción recomendada | G4: Responsable | H4: Plazo | I4: Evidencia de cierre | J4: Estado | K4: Observaciones
A5: =ASSESSMENT!A7 -> 1 | B5: =ASSESSMENT!B7 -> Gobierno y responsabilidad proactiva | C5: =ASSESSMENT!D7 -> Política de protección de datos personales para la empresa | D5: =ASSESSMENT!P7 -> Pendiente | E5: =ASSESSMENT!U7 -> Pendiente | F5: =ASSESSMENT!T7 -> Aprobar o actualizar la política interna, comunicarla formalmente y definir revisión anual. | G5: =ASSESSMENT!V7 -> 0 | H5: =ASSESSMENT!W7 -> Por definir | I5: =ASSESSMENT!X7 -> 0 | J5: =ASSESSMENT!Y7 -> Pendiente | K5: =ASSESSMENT!Z7 -> 0
A6: =ASSESSMENT!A8 -> 2 | B6: =ASSESSMENT!B8 -> Gobierno y responsabilidad proactiva | C6: =ASSESSMENT!D8 -> Roles, responsabilidades y sponsor ejecutivo | D6: =ASSESSMENT!P8 -> Pendiente | E6: =ASSESSMENT!U8 -> Pendiente | F6: =ASSESSMENT!T8 -> Definir responsables internos por proceso y formalizar su rol con soporte de gerencia. | G6: =ASSESSMENT!V8 -> 0 | H6: =ASSESSMENT!W8 -> Por definir | I6: =ASSESSMENT!X8 -> 0 | J6: =ASSESSMENT!Y8 -> Pendiente | K6: =ASSESSMENT!Z8 -> 0
A7: =ASSESSMENT!A9 -> 3 | B7: =ASSESSMENT!B9 -> Gobierno y responsabilidad proactiva | C7: =ASSESSMENT!D9 -> Evaluación de aplicabilidad y designación del DPD | D7: =ASSESSMENT!P9 -> Pendiente | E7: =ASSESSMENT!U9 -> Pendiente | F7: =ASSESSMENT!T9 -> Documentar la evaluación de aplicabilidad del DPD y, si corresponde, formalizar nombramiento, registro, canal y alcance. | G7: =ASSESSMENT!V9 -> 0 | H7: =ASSESSMENT!W9 -> Por definir | I7: =ASSESSMENT!X9 -> 0 | J7: =ASSESSMENT!Y9 -> Pendiente | K7: =ASSESSMENT!Z9 -> 0
A8: =ASSESSMENT!A10 -> 4 | B8: =ASSESSMENT!B10 -> Gobierno y responsabilidad proactiva | C8: =ASSESSMENT!D10 -> Independencia, recursos y seguimiento del DPD cuando aplique | D8: =ASSESSMENT!P10 -> Pendiente | E8: =ASSESSMENT!U10 -> Pendiente | F8: =ASSESSMENT!T10 -> Formalizar independencia, línea de reporte, recursos y seguimiento de recomendaciones del DPD cuando aplique. | G8: =ASSESSMENT!V10 -> 0 | H8: =ASSESSMENT!W10 -> Por definir | I8: =ASSESSMENT!X10 -> 0 | J8: =ASSESSMENT!Y10 -> Pendiente | K8: =ASSESSMENT!Z10 -> 0
A9: =ASSESSMENT!A11 -> 5 | B9: =ASSESSMENT!B11 -> Gobierno y responsabilidad proactiva | C9: =ASSESSMENT!D11 -> Mapa de obligaciones y base normativa aplicable | D9: =ASSESSMENT!P11 -> Pendiente | E9: =ASSESSMENT!U11 -> Pendiente | F9: =ASSESSMENT!T11 -> Elaborar matriz de obligaciones aplicables y vincularlas con controles internos. | G9: =ASSESSMENT!V11 -> 0 | H9: =ASSESSMENT!W11 -> Por definir | I9: =ASSESSMENT!X11 -> 0 | J9: =ASSESSMENT!Y11 -> Pendiente | K9: =ASSESSMENT!Z11 -> 0
A10: =ASSESSMENT!A12 -> 6 | B10: =ASSESSMENT!B12 -> Gobierno y responsabilidad proactiva | C10: =ASSESSMENT!D12 -> Presupuesto y recursos | D10: =ASSESSMENT!P12 -> Pendiente | E10: =ASSESSMENT!U12 -> Pendiente | F10: =ASSESSMENT!T12 -> Definir presupuesto proporcional al riesgo para sostener cumplimiento y seguridad. | G10: =ASSESSMENT!V12 -> 0 | H10: =ASSESSMENT!W12 -> Por definir | I10: =ASSESSMENT!X12 -> 0 | J10: =ASSESSMENT!Y12 -> Pendiente | K10: =ASSESSMENT!Z12 -> 0
A11: =ASSESSMENT!A13 -> 7 | B11: =ASSESSMENT!B13 -> Gobierno y responsabilidad proactiva | C11: =ASSESSMENT!D13 -> Gestión documental del SGPDP | D11: =ASSESSMENT!P13 -> Pendiente | E11: =ASSESSMENT!U13 -> Pendiente | F11: =ASSESSMENT!T13 -> Crear control maestro documental para políticas, matrices, procedimientos y evidencias. | G11: =ASSESSMENT!V13 -> 0 | H11: =ASSESSMENT!W13 -> Por definir | I11: =ASSESSMENT!X13 -> 0 | J11: =ASSESSMENT!Y13 -> Pendiente | K11: =ASSESSMENT!Z13 -> 0
A12: =ASSESSMENT!A14 -> 8 | B12: =ASSESSMENT!B14 -> Gobierno y responsabilidad proactiva | C12: =ASSESSMENT!D14 -> Indicadores y reportes a dirección | D12: =ASSESSMENT!P14 -> Pendiente | E12: =ASSESSMENT!U14 -> Pendiente | F12: =ASSESSMENT!T14 -> Definir indicadores mínimos y reportarlos periódicamente a dirección. | G12: =ASSESSMENT!V14 -> 0 | H12: =ASSESSMENT!W14 -> Por definir | I12: =ASSESSMENT!X14 -> 0 | J12: =ASSESSMENT!Y14 -> Pendiente | K12: =ASSESSMENT!Z14 -> 0
A13: =ASSESSMENT!A15 -> 9 | B13: =ASSESSMENT!B15 -> Inventario, RAT, finalidades y legitimación | C13: =ASSESSMENT!D15 -> Inventario de tratamientos de la empresa | D13: =ASSESSMENT!P15 -> Pendiente | E13: =ASSESSMENT!U15 -> Pendiente | F13: =ASSESSMENT!T15 -> Levantar o actualizar inventario de tratamientos con dueños por proceso. | G13: =ASSESSMENT!V15 -> 0 | H13: =ASSESSMENT!W15 -> Por definir | I13: =ASSESSMENT!X15 -> 0 | J13: =ASSESSMENT!Y15 -> Pendiente | K13: =ASSESSMENT!Z15 -> 0
A14: =ASSESSMENT!A16 -> 10 | B14: =ASSESSMENT!B16 -> Inventario, RAT, finalidades y legitimación | C14: =ASSESSMENT!D16 -> Registro de Actividades de Tratamiento (RAT) | D14: =ASSESSMENT!P16 -> Pendiente | E14: =ASSESSMENT!U16 -> Pendiente | F14: =ASSESSMENT!T16 -> Construir o actualizar RAT con base en procesos reales y evidencia de validación. | G14: =ASSESSMENT!V16 -> 0 | H14: =ASSESSMENT!W16 -> Por definir | I14: =ASSESSMENT!X16 -> 0 | J14: =ASSESSMENT!Y16 -> Pendiente | K14: =ASSESSMENT!Z16 -> 0
A15: =ASSESSMENT!A17 -> 11 | B15: =ASSESSMENT!B17 -> Inventario, RAT, finalidades y legitimación | C15: =ASSESSMENT!D17 -> Finalidades específicas y documentadas | D15: =ASSESSMENT!P17 -> Pendiente | E15: =ASSESSMENT!U17 -> Pendiente | F15: =ASSESSMENT!T17 -> Depurar finalidades y eliminar descripciones genéricas o incompatibles. | G15: =ASSESSMENT!V17 -> 0 | H15: =ASSESSMENT!W17 -> Por definir | I15: =ASSESSMENT!X17 -> 0 | J15: =ASSESSMENT!Y17 -> Pendiente | K15: =ASSESSMENT!Z17 -> 0
A16: =ASSESSMENT!A18 -> 12 | B16: =ASSESSMENT!B18 -> Inventario, RAT, finalidades y legitimación | C16: =ASSESSMENT!D18 -> Base de legitimación por tratamiento | D16: =ASSESSMENT!P18 -> Pendiente | E16: =ASSESSMENT!U18 -> Pendiente | F16: =ASSESSMENT!T18 -> Validar bases de legitimación por proceso y documentar rationale. | G16: =ASSESSMENT!V18 -> 0 | H16: =ASSESSMENT!W18 -> Por definir | I16: =ASSESSMENT!X18 -> 0 | J16: =ASSESSMENT!Y18 -> Pendiente | K16: =ASSESSMENT!Z18 -> 0
... A84: =ASSESSMENT!A86 -> 80 | B84: =ASSESSMENT!B86 -> Capacitación, cultura, auditoría y mejora continua | C84: =ASSESSMENT!D86 -> Mejora continua y revisión por dirección | D84: =ASSESSMENT!P86 -> Pendiente | E84: =ASSESSMENT!U86 -> Pendiente | F84: =ASSESSMENT!T86 -> Establecer revisión por dirección y hoja de ruta anual. | G84: =ASSESSMENT!V86 -> 0 | H84: =ASSESSMENT!W86 -> Por definir | I84: =ASSESSMENT!X86 -> 0 | J84: =ASSESSMENT!Y86 -> Pendiente | K84: =ASSESSMENT!Z86 -> 0

Sheet Catálogos
A1: Catálogos del modelo
A2: Aplica | B2: Sí | C2: No
A3: Nivel asignado (1-5) | B3: 1 | C3: 2 | D3: 3
B4: 4 | C4: 5
A5: Nivel evidencia (0-4) | B5: 0 | C5: 1 | D5: 2
B6: 3 | C6: 4
A7: Bloqueante | B7: Sí | C7: No
A8: Prioridad | B8: Crítica | C8: Alta | D8: Media
B9: Baja | C9: Pendiente
A10: Estado del plan | B10: Pendiente | C10: En proceso | D10: Cerrado
B11: No iniciado | C11: No aplica
A12: Criterio evidencia 0 | B12: Sin evidencia / declaración verbal
A13: Criterio evidencia 1 | B13: Evidencia informal: correo, captura, práctica no formalizada
A14: Criterio evidencia 2 | B14: Evidencia documental: política, matriz, procedimiento, contrato
A15: Criterio evidencia 3 | B15: Evidencia operativa: registros, bitácoras, actas, solicitudes atendidas
A16: Criterio evidencia 4 | B16: Evidencia gestionada: indicadores, auditoría, revisión y mejora

Sheet Base Normativa
A1: Base normativa y técnica de referencia para empresas del sector comercio
A2: Referencia | B2: Uso en el assessment | C2: Naturaleza | D2: Dimensiones vinculadas | E2: Nota para el consultor
A3: Constitución de la República del Ecuador | B3: Derecho a la protección de datos personales, acceso y decisión sobre información personal. | C3: Base constitucional | D3: Todas | E3: Usar como fundamento general de derechos.
A4: Ley Orgánica de Protección de Datos Personales | B4: Principios, derechos, obligaciones del responsable/encargado, seguridad, RAT, DPD, incidentes y régimen aplicable. | C4: Obligación legal | D4: Todas | E4: Validar siempre con versión oficial vigente.
A5: Reglamento General a la LOPDP | B5: Desarrollo de medidas, derechos, seguridad, evaluación de impacto, privacidad desde el diseño, roles y evidencias. | C5: Obligación reglamentaria | D5: Gobierno, derechos, seguridad, riesgos | E5: Aplicar con enfoque proporcional al tamaño, canales, volumen y riesgo de la empresa.
A6: Normativa secundaria y guías de la SPDP | B6: Criterios sobre riesgos, EIPD, privacidad desde el diseño, DPD, contratos, transferencias e interés legítimo cuando aplique. | C6: Normativa / guía oficial | D6: Riesgos, DPD, proveedores, contratos | E6: Diferenciar obligación jurídica, normativa secundaria, guía y buena práctica.
A7: Ley Orgánica de Defensa del Consumidor | B7: Contexto de relación con clientes, información, atención, reclamos, garantías y prácticas comerciales cuando corresponda. | C7: Normativa relacionada / cuando aplique | D7: Transparencia, atención, procesos comerciales | E7: No sustituye el análisis específico de protección de datos; validar aplicabilidad al negocio.
A8: Ley de Comercio Electrónico, Firmas Electrónicas y Mensajes de Datos | B8: Contexto para contratación, mensajes de datos, transacciones y canales electrónicos cuando corresponda. | C8: Normativa relacionada / cuando aplique | D8: Canales digitales, e-commerce, evidencias | E8: Validar especialmente en ventas y contratación por medios electrónicos.
A9: Normativa tributaria, societaria, laboral y de conservación aplicable | B9: Puede justificar determinados datos, documentos y plazos de conservación en facturación, contabilidad, contratos y RR. HH. | C9: Obligación sectorial/transversal según actividad | D9: Conservación, RR. HH., procesos comerciales | E9: No fijar plazos genéricos: documentar fundamento específico por categoría documental.
A10: Buenas prácticas de seguridad de la información | B10: Accesos, MFA, endpoints, respaldos, registros, cifrado, nube, proveedores, vulnerabilidades e incidentes. | C10: Buena práctica técnica | D10: Seguridad, incidentes, proveedores | E10: Usar de forma proporcional; no presentar como certificación si no existe.
A11: Modelo de madurez SMARTCIDI | B11: Evalúa madurez 1-5 combinando nivel asignado, evidencia, criticidad, bloqueantes y plan de acción. | C11: Metodología consultiva | D11: Todas | E11: Sirve para diagnóstico, priorización y hoja de ruta; no equivale a certificación legal.

Sheet Guía Aplicación Comercio
A1: Guía de Aplicación del Assessment SGPDP para Empresas del Sector Comercio
A2: Objetivo | B2: Medir el nivel de madurez del Sistema de Gestión de Protección de Datos Personales de una empresa comercial ecuatoriana, considerando LOPDP, riesgos, evidencia y operación real en canales físicos y digitales.
A3: Cómo aplicar | B3: 1) Completar 'Perfil Comercio'. 2) Confirmar alcance: matriz, tiendas/sucursales, POS, ERP, CRM, e-commerce, pagos, logística, proveedores y canales. 3) Entrevistar áreas. 4) Solicitar evidencias. 5) Completar Aplica, Nivel asignado y Nivel evidencia. 6) Revisar Dashboard y Plan de Acción.
A5: Campo | B5: Qué significa | C5: Valores permitidos | D5: Cómo decidir | E5: Ejemplo comercio | F5: Impacto en el cálculo
A6: Aplica | B6: Determina si el control entra o no al cálculo. | C6: Sí / No | D6: Marcar No solo si el control realmente no corresponde al modelo de negocio. No usar No para ocultar una brecha. En caso de duda, mantener Sí hasta validar. | E6: E-commerce puede ser No en un comercio exclusivamente físico; transferencia internacional solo después de validar nube, SaaS y proveedores. | F6: Si No: se excluye del score y riesgo.
A7: Criticidad | B7: Peso del control dentro de la madurez. No mide cumplimiento, mide importancia. | C7: 1 a 5 | D7: 5 para controles estructurales o de alto riesgo: RAT, derechos, incidentes, seguridad, POS/pagos, e-commerce, proveedores críticos. Ajustar según contexto. | E7: Pagos/POS o e-commerce = 5 cuando aplican; capacitación general = 3. | F7: A mayor criticidad, mayor peso y mayor brecha si el nivel es bajo.
A8: Nivel asignado | B8: Madurez observada del control según entrevista y revisión. | C8: 1 a 5 | D8: 1 no existe; 2 parcial; 3 documentado; 4 aplicado con evidencias; 5 medido y mejorado. | E8: Existe procedimiento de derechos, pero no hay registros de aplicación: nivel 3 como máximo. | F8: Se combina con evidencia para obtener nivel efectivo.
A9: Nivel evidencia | B9: Calidad de la evidencia que respalda el nivel asignado. | C9: 0 a 4 | D9: 0 verbal; 1 informal; 2 documental; 3 operativa; 4 revisada con indicadores/auditoría. | E9: Política aprobada = 2; solicitudes atendidas con registro = 3; indicadores revisados por dirección/DPD = 4. | F9: Limita el nivel efectivo mediante MIN(Nivel asignado, Evidencia+1).
A10: Nivel efectivo | B10: Nivel real reconocido por el modelo después de validar evidencia. | C10: Automático | D10: No se llena manualmente. | E10: Si asigna 5 pero evidencia 2, el nivel efectivo será 3. | F10: Base del score y del riesgo de brecha.
A11: Score ponderado | B11: Puntaje obtenido por el control. | C11: Automático | D11: Fórmula: Nivel efectivo / 5 × Criticidad. | E11: Control crítico de pago/POS con nivel efectivo 3 suma 3 puntos de 5 posibles. | F11: Suma al score de dimensión y global.
A12: Riesgo de brecha | B12: Criticidad de lo que falta para llegar a madurez 5. | C12: Automático | D12: Fórmula conceptual: (5 - Nivel efectivo) × Criticidad. | E12: Procedimiento de incidentes con nivel 1 y criticidad 5 = brecha crítica. | F12: Prioriza acciones del plan.
A13: Bloqueante de madurez | B13: Control que impide declarar una madurez alta si está débil. | C13: Sí / No | D13: Marcar Sí en controles esenciales: RAT, derechos, incidentes, seguridad, gobierno y procesos comerciales críticos. | E13: No tener RAT, procedimiento de derechos, incidentes o controles críticos de seguridad no debe permitir declarar madurez alta. | F13: Dashboard limita el nivel final ajustado.
A15: Escala de madurez | B15: Criterio resumido | C15: Evidencia esperada
A16: Nivel 1 - Inicial / Reactivo | B16: No existe o se gestiona informalmente. | C16: Declaraciones verbales o prácticas aisladas.
A17: Nivel 2 - Básico / Repetible | B17: Existe parcialmente o depende de personas; no está integrado. | C17: Borradores, correos, controles informales.
A18: Nivel 3 - Definido / Documentado | B18: Existe documento, responsable y criterio aprobado. | C18: Políticas, matrices, procedimientos, contratos, registros básicos.
A19: Nivel 4 - Gestionado / Demostrable | B19: Se aplica y se revisa con evidencia periódica. | C19: Actas, bitácoras, solicitudes atendidas, revisiones, reportes.
A20: Nivel 5 - Optimizado / Mejora continua | B20: Se mide, audita, corrige y mejora continuamente. | C20: Indicadores, auditoría, revisión por dirección/DPO, mejoras implementadas.
A22: Reglas prácticas para el consultor | B22: 1) Si el control debería existir y no existe: Aplica=Sí, Nivel=1, Evidencia=0. 2) Si solo hay documento sin uso: nivel máximo sugerido=3. 3) Si hay registros de aplicación: nivel 4. 4) Si hay indicadores y mejora continua: nivel 5. 5) Si no se sabe si aplica, no marcar No hasta validar. 6) En comercios omnicanal revisar coherencia entre tienda física, web/e-commerce, CRM, POS, pagos y logística.
A23: Entregables esperados | B23: Perfil de contexto validado, Dashboard ejecutivo, madurez por dimensión, brechas críticas/altas, bloqueantes, plan de acción 30/60/90/180 días y evidencias requeridas.

Sheet Procesos Comercio
A1: Procesos comerciales sugeridos para revisar durante el assessment
A2: Proceso | B2: Datos personales típicos | C2: Titulares | D2: Riesgos frecuentes | E2: Evidencia a solicitar
A3: Captación, registro y actualización de clientes | B3: Identificación, contacto, preferencias, cuenta de cliente, historial básico, origen del lead. | C3: Prospectos / clientes | D3: Recolección excesiva, origen no trazable, falta de aviso, datos desactualizados. | E3: Formularios, CRM, ficha de cliente, avisos, matrices de datos y bases de legitimación.
A4: Venta presencial, POS y facturación | B4: Identificación cuando corresponde, factura, datos de contacto, compra, comprobantes, vendedor/caja. | C4: Clientes | D4: Exposición en caja, permisos excesivos, impresión innecesaria, exportaciones sin control. | E4: Configuración POS, facturas, perfiles de caja, logs, procedimiento de venta.
A5: E-commerce y cuentas de usuario | B5: Registro, correo/teléfono, credenciales, carrito, pedidos, historial, direcciones, cookies cuando apliquen. | C5: Usuarios / clientes | D5: Campos excesivos, cuentas comprometidas, cookies/trackers sin revisión, integraciones no controladas. | E5: Flujo de registro/checkout, aviso, cookies, logs, integraciones, contrato de plataforma.
A6: Pagos, pasarelas y prevención de fraude | B6: Datos de transacción, referencia de pago, medio de pago, señales antifraude; datos de tarjeta solo según arquitectura. | C6: Clientes | D6: Almacenamiento innecesario, terceros no evaluados, exposición en logs, fraude o accesos indebidos. | E6: Contratos con pasarelas/adquirentes, flujo de pago, configuración, logs, controles antifraude.
A7: CRM, fidelización y marketing | B7: Contacto, historial/segmentos, preferencias, campañas, puntos/beneficios, respuestas. | C7: Prospectos / clientes | D7: Listas sin base, perfilamiento opaco, falta de oposición/baja, reutilización incompatible. | E7: CRM, formularios de fidelización, campañas, preferencias, bajas, consentimientos cuando apliquen.
A8: Servicio al cliente, devoluciones, garantías y reclamos | B8: Identificación, pedido/factura, motivo, contacto, evidencias, tickets y comunicaciones. | C8: Clientes / usuarios | D8: Pedir más datos de los necesarios, revelar historial, mala verificación de identidad. | E8: Tickets, formularios, guiones, procedimiento, registros de verificación y respuestas.
A9: Logística, despacho, entrega y retiro | B9: Nombre, teléfono, dirección, pedido, instrucciones de entrega, evidencia de recepción. | C9: Clientes / destinatarios | D9: Etiquetas visibles, acceso excesivo, couriers sin control, conservación indefinida. | E9: Órdenes de despacho, etiquetas, contratos con couriers, perfiles y comprobantes de entrega.
A10: Talento humano | B10: Expedientes laborales, selección, nómina, afiliaciones, salud ocupacional cuando aplique, accesos. | C10: Colaboradores / postulantes | D10: Acceso excesivo, conservación indefinida, bajas tardías, datos sensibles sin controles. | E10: Expedientes, avisos laborales, confidencialidad, bajas de usuarios, matriz de accesos.
A11: Proveedores y encargados | B11: Datos corporativos y personales; acceso de terceros a CRM, POS, ERP, nube, logística, marketing, soporte. | C11: Clientes / colaboradores / proveedores | D11: Contratos sin cláusulas, soporte sin trazabilidad, subencargados y transferencias no identificadas. | E11: Inventario de proveedores, contratos/DPA, due diligence, SLA y evidencias de seguridad.
A12: Archivo físico/digital y conservación | B12: Facturas, contratos, expedientes, reclamos, RR. HH., pedidos, reportes y respaldos. | C12: Todos los titulares | D12: Acumulación, eliminación insegura, permisos excesivos, duplicados y copias locales. | E12: Tabla de conservación, inventario, políticas de archivo, permisos, actas/certificados de eliminación.
A13: Incidentes y continuidad | B13: Datos afectados por pérdida, acceso indebido, malware, cuenta comprometida, envío erróneo o indisponibilidad. | C13: Todos los titulares | D13: Falta de detección, registro, contención, evaluación de impacto o escalamiento. | E13: Procedimiento, registro de incidentes, simulacros, tickets, lecciones aprendidas y planes de mejora.

Sheet Perfil Comercio
A1: Perfil de contexto y alcance - Empresa del Sector Comercio
A2: Completar antes del assessment. Estas variables ayudan a decidir aplicabilidad, criticidad, entrevistas y evidencias; para estimar esfuerzo, duración y presupuesto utilizar la hoja 'Dimensionamiento Servicios'.
A4: Variable | B4: Qué validar | C4: Respuesta / dato | D4: Riesgo o impacto en el assessment | E4: Evidencia sugerida | F4: Estado
A5: Tipo de comercio | B5: Retail, mayorista, distribuidor, e-commerce, marketplace, franquicia u omnicanal. | D5: Define procesos y canales a evaluar. | E5: RUC/objeto, organigrama, descripción operativa. | F5: Por validar
A6: Número de tiendas / sucursales | B6: Locales, bodegas, centros de distribución y oficinas. | D6: Aumenta dispersión de accesos, CCTV, archivos y usuarios. | E6: Listado de ubicaciones. | F6: Por validar
A7: Número de empleados / usuarios con acceso | B7: Personal propio, temporal y terceros con cuentas. | D7: Dimensiona gestión de identidades, capacitación y bajas. | E7: Nómina y listado de usuarios. | F7: Por validar
A8: Volumen aproximado de clientes activos | B8: Clientes identificados y cuentas registradas. | D8: Influye en escala, riesgo y esfuerzo de derechos/incidentes. | E8: CRM/ERP/POS, reportes. | F8: Por validar
A9: Volumen histórico de registros | B9: Clientes, prospectos, pedidos y facturas conservados. | D9: Afecta conservación, eliminación, riesgo de exposición y migraciones. | E9: Reportes de bases/repositorios. | F9: Por validar
A10: POS / sistema de cajas | B10: Proveedor, arquitectura, usuarios, datos capturados, integración con ERP/CRM. | D10: Proceso crítico en comercio presencial. | E10: Contrato, matriz de accesos, configuración. | F10: Por validar
A11: ERP / facturación / inventario | B11: Sistemas, módulos y datos personales incluidos. | D11: Puede centralizar datos de clientes, personal y proveedores. | E11: Inventario de sistemas y contratos. | F11: Por validar
A12: CRM | B12: Plataforma, finalidades, usuarios, integraciones, marketing y exportaciones. | D12: Alto impacto en prospección, campañas y fidelización. | E12: DPA/contrato, perfiles, flujos. | F12: Por validar
A13: E-commerce / app | B13: Plataforma, cuentas, checkout, pedidos, cookies e integraciones. | D13: Activa controles específicos de canales digitales. | E13: URL, contrato, configuración, mapa de integraciones. | F13: Por validar
A14: Pasarelas / medios de pago | B14: Proveedores, datos visibles/almacenados, tokenización y antifraude. | D14: Flujo de alto riesgo; delimitar responsabilidades y almacenamiento. | E14: Contratos, diagrama de pago, configuración. | F14: Por validar
A15: Programa de fidelización | B15: Puntos, perfil de cliente, preferencias, segmentos y beneficios. | D15: Puede aumentar perfilamiento y reutilización de datos. | E15: Términos, formulario, CRM, reglas del programa. | F15: Por validar
A16: Marketing y automatización | B16: Email/SMS/WhatsApp, audiencias, pixels, listas, plataformas y fuentes. | D16: Requiere trazabilidad de origen, oposición y bases. | E16: Plataformas, campañas, formularios, consentimientos. | F16: Por validar
... A29: Incidentes previos | B29: Pérdida, phishing, cuentas comprometidas, envíos erróneos, malware o fuga. | D29: Ajusta riesgo y priorización del plan de acción. | E29: Registro de incidentes/tickets. | F29: Por validar

Sheet Dimensionamiento
A1: HOJA HISTÓRICA – NO UTILIZAR PARA NUEVAS COTIZACIONES. Use la hoja “Dimensionamiento Servicios” (modelo v1.3).
A2: Herramienta interna SMARTCIDI para estimar el alcance de una consultoría LOPDP en empresas del sector comercio. Complete los campos amarillos; ingrese 0 cuando una categoría numérica haya sido validada y no aplique. El resultado es una estimación comercial basada en escala, complejidad, riesgo, tecnología y madurez; no es una exigencia legal ni sustituye el diagnóstico.
A4: Cobertura de información | B4: =(COUNTA(C20:C30)+COUNTA(C35:C42)+COUNTA(C46:C51)+COUNTA(C55:C61))/32 -> 0 | C4: Índice de complejidad | D4: =IF(OR(B4<0.6,COUNT(C25:C30)=0),"",B70) | E4: Nivel | F4: =IF(OR(B4<0.6,COUNT(C25:C30)=0),"Información insuficiente",IF(D4<=25,"Baja",IF(D4<=50,"Media",IF(D4<=75,"Alta","Muy alta")))) -> Información insuficiente | G4: Esfuerzo central | H4: =IF(OR(B4<0.6,COUNT(C25:C30)=0),"",$C$14+D4*$C$15)
A5: Duración estimada | B5: =IF(OR(OR(B4<0.6,COUNT(C25:C30)=0),$C$11<=0),"",ROUNDUP(H4/$C$11,0)) | C5: Presupuesto objetivo* | D5: =IF(OR(OR(B4<0.6,COUNT(C25:C30)=0),$C$10<=0),"",H4*$C$10*(1+$C$12)*$C$13) | E5: Presupuesto mínimo* | F5: =IF(D5="","",D5*(1-$C$16)) | G5: Presupuesto máximo* | H5: =IF(D5="","",D5*(1+$C$16))
A7: Equipo sugerido | B7: =IF(OR(B4<0.6,COUNT(C25:C30)=0),"Completar información para estimar",IF(D4<=25,"1 consultor líder + apoyo puntual",IF(D4<=50,"1 consultor líder + 1 especialista",IF(D4<=75,"2 consultores / especialistas","Equipo multidisciplinario de 2 a 3+ perfiles")))) -> Completar información para estimar
A8: Alcance sugerido | B8: =IF(OR(B4<0.6,COUNT(C25:C30)=0),"Completar información para estimar",IF(D4<=25,"Assessment + implementación base",IF(D4<=50,"Proyecto estándar de diagnóstico e implementación",IF(D4<=75,"Proyecto ampliado con remediación priorizada","Proyecto complejo por fases / oleadas")))) -> Completar información para estimar
A9: Parámetros comerciales SMARTCIDI (editables)
A10: Tarifa interna referencial (sin impuestos) | B10: USD por hora. Ingresar la tarifa comercial interna de SMARTCIDI antes de impuestos. | C10: 0 | D10: USD/h | H10: Si se deja en 0, el presupuesto no se calcula.
A11: Capacidad asignada al proyecto | B11: Horas efectivas por semana que el equipo puede dedicar a esta consultoría. | C11: 12 | D11: h/semana | H11: Afecta la duración, no el esfuerzo total.
A12: Contingencia del proyecto | B12: Reserva por coordinación, retrabajo, validaciones y hallazgos no previstos. | C12: 0.15 | D12: % | H12: Parámetro comercial interno.
A13: Factor comercial | B13: Ajuste por posicionamiento, complejidad contractual o estrategia comercial. | C13: 1 | D13: factor | H13: 1,00 = sin ajuste.
A14: Horas base | B14: Esfuerzo mínimo para movilización, levantamiento, análisis y cierre. | C14: 40 | D14: horas | H14: Base del modelo.
A15: Horas por punto de complejidad | B15: Pendiente que convierte el índice 0-100 en horas adicionales. | C15: 2.1 | D15: h/punto | H15: Editable con experiencia histórica SMARTCIDI.
A16: Margen del rango presupuestario | B16: Rango inferior/superior respecto del presupuesto objetivo. | C16: 0.1 | D16: % | H16: Permite presentar una banda de negociación.
A18: A. Escala, volumen y estructura operativa
A19: Variable | B19: Qué debe informar la empresa | C19: Respuesta / dato | D19: Unidad / opciones | E19: Score | F19: Peso interno | G19: Aporte | H19: Impacto en el alcance
A20: Número de empleados | B20: Personal propio y terceros recurrentes que participan en la operación. | D20: personas | E20: =IF(C20="","",IF(C20<=20,10,IF(C20<=50,25,IF(C20<=100,45,IF(C20<=250,65,IF(C20<=500,85,100)))))) | F20: 0.3 | G20: =IF(E20="","",E20*F20) | H20: Dimensiona usuarios, capacitación, accesos y número de entrevistas.
A21: Número de sucursales / locales | B21: Tiendas, oficinas, bodegas y centros de distribución con operación propia. | D21: ubicaciones | E21: =IF(C21="","",IF(C21<=1,10,IF(C21<=3,25,IF(C21<=10,50,IF(C21<=25,75,100))))) | F21: 0.2 | G21: =IF(E21="","",E21*F21) | H21: Aumenta dispersión de archivos, CCTV, usuarios y variaciones de proceso.
A22: Número de áreas con tratamiento | B22: Áreas o unidades que recolectan, usan, consultan o conservan datos personales. | D22: áreas | E22: =IF(C22="","",IF(C22<=3,10,IF(C22<=5,25,IF(C22<=8,50,IF(C22<=12,75,100))))) | F22: 0.25 | G22: =IF(E22="","",E22*F22) | H22: Determina entrevistas, responsables y cobertura del levantamiento.
A23: Número de procesos con datos personales | B23: Procesos identificados que involucran datos personales. | D23: procesos | E23: =IF(C23="","",IF(C23<=5,10,IF(C23<=10,30,IF(C23<=20,55,IF(C23<=35,80,100))))) | F23: 0.35 | G23: =IF(E23="","",E23*F23) | H23: Variable directa del esfuerzo para inventario, RAT y evidencias.
A24: Documentación de procesos | B24: Nivel en que los procesos están levantados, documentados y actualizados. | D24: seleccionar | E24: =IF(C24="","",IF(C24="Completa y actualizada",0,IF(C24="Parcialmente documentados",40,IF(C24="Documentación informal",70,IF(C24="No documentados",100,80))))) | F24: 0.2 | G24: =IF(E24="","",E24*F24) | H24: Si no existen procesos documentados, aumenta el esfuerzo de descubrimiento antes del análisis LOPDP.
A25: Clientes activos | B25: Clientes identificados o cuentas activas. | D25: titulares | H25: Parte del volumen total de titulares.
A26: Clientes históricos | B26: Registros históricos conservados de clientes, pedidos o facturación. | D26: titulares | H26: Afecta conservación, archivo y volumen de datos.
A27: Prospectos / leads | B27: Contactos de campañas, formularios, CRM, redes sociales u otros canales. | D27: titulares | H27: Aumenta complejidad de marketing, trazabilidad y oposición.
A28: Empleados / extrabajadores | B28: Personal actual e histórico con expedientes conservados. | D28: titulares | H28: Incluye tratamiento laboral y conservación documental.
A29: Proveedores / contactos | B29: Personas naturales y contactos identificables de proveedores. | D29: titulares | H29: Incluye gestión contractual y terceros.
A30: Otros titulares | B30: Visitantes, usuarios web, destinatarios, candidatos u otros no incluidos arriba. | D30: titulares | H30: Completa la estimación de escala.
A31: Total estimado de titulares | B31: Suma de categorías declaradas. Puede contener duplicados; se usa solo para dimensionamiento. | C31: =IF(COUNT(C25:C30)=0,"",SUM(C25:C30)) | D31: titulares | E31: =IF(COUNT(C25:C30)=0,"",IF(C31<=1000,10,IF(C31<=5000,25,IF(C31<=25000,45,IF(C31<=100000,65,IF(C31<=500000,85,100)))))) | F31: 0.7 | G31: =IF(E31="","",E31*F31) | H31: Proxy de volumen, no equivale a titulares únicos.
A33: B. Sensibilidad, riesgo y tratamientos de mayor impacto
A34: Variable | B34: Qué debe informar la empresa | C34: Respuesta / dato | D34: Unidad / opciones | E34: Score | F34: Peso interno | G34: Aporte | H34: Impacto en el alcance
A35: Datos sensibles | B35: ¿Trata datos de salud, biométricos, origen étnico, creencias, vida sexual u otras categorías sensibles según la LOPDP? | D35: Sí / No / No sabe | E35: =IF(C35="","",IF(C35="Sí",100,IF(C35="No",0,60))) | F35: 0.2 | G35: =IF(E35="","",E35*F35) | H35: Eleva el análisis de riesgo, medidas de seguridad y posible EIPD según contexto.
A36: Niñas, niños o adolescentes | B36: ¿Trata datos personales de personas menores de edad? | D36: Sí / No / No sabe | E36: =IF(C36="","",IF(C36="Sí",100,IF(C36="No",0,60))) | F36: 0.15 | G36: =IF(E36="","",E36*F36) | H36: Implica protección reforzada y puede activar obligaciones adicionales.
A37: Biometría | B37: ¿Usa huella, rostro u otros patrones biométricos para identificación o control? | D37: Sí / No / No sabe | E37: =IF(C37="","",IF(C37="Sí",100,IF(C37="No",0,60))) | F37: 0.15 | G37: =IF(E37="","",E37*F37) | H37: Tratamiento de alto impacto que requiere revisión específica.
A38: CCTV / videovigilancia | B38: ¿Opera cámaras en tiendas, bodegas, oficinas o zonas de atención? | D38: Sí / No / No sabe | E38: =IF(C38="","",IF(C38="Sí",100,IF(C38="No",0,60))) | F38: 0.1 | G38: =IF(E38="","",E38*F38) | H38: Añade finalidades, avisos, retención, accesos y terceros de seguridad.
A39: Geolocalización | B39: ¿Usa ubicación de clientes, repartidores, flota o app? | D39: Sí / No / No sabe | E39: =IF(C39="","",IF(C39="Sí",100,IF(C39="No",0,60))) | F39: 0.05 | G39: =IF(E39="","",E39*F39) | H39: Puede incrementar el impacto sobre privacidad y requerir minimización reforzada.
A40: Perfilamiento / scoring | B40: ¿Segmenta, recomienda, califica riesgo/fraude o construye perfiles comerciales? | D40: Sí / No / No sabe | E40: =IF(C40="","",IF(C40="Sí",100,IF(C40="No",0,60))) | F40: 0.15 | G40: =IF(E40="","",E40*F40) | H40: Requiere revisar transparencia, bases, oposición y decisiones automatizadas cuando apliquen.
A41: Incidentes últimos 24 meses | B41: ¿Ha existido pérdida, phishing, cuenta comprometida, envío erróneo, malware o fuga de información? | D41: Sí / No / No sabe | E41: =IF(C41="","",IF(C41="Sí",100,IF(C41="No",0,60))) | F41: 0.1 | G41: =IF(E41="","",E41*F41) | H41: Puede añadir remediación y revisión técnica/organizativa.
A42: Datos financieros / patrimoniales | B42: ¿Trata información financiera o patrimonial más allá de datos mínimos de facturación/pago? | D42: Sí / No / No sabe | E42: =IF(C42="","",IF(C42="Sí",100,IF(C42="No",0,60))) | F42: 0.1 | G42: =IF(E42="","",E42*F42) | H42: Aumenta impacto potencial y controles de acceso.
A43: Detalle de datos sensibles / procesos | B43: Si respondió Sí en datos sensibles, indique qué categorías se tratan y en qué procesos o sistemas. | D43: texto libre | H43: Permite dimensionar entrevistas, análisis de riesgo, seguridad y posibles EIPD.
A44: C. Tecnología, canales y terceros
A45: Variable | B45: Qué debe informar la empresa | C45: Respuesta / dato | D45: Unidad / opciones | E45: Score | F45: Peso interno | G45: Aporte | H45: Impacto en el alcance
A46: Número de sistemas / plataformas | B46: ERP, POS, CRM, e-commerce, nómina, nube, marketing, CCTV, biometría y otros. | D46: sistemas | E46: =IF(C46="","",IF(C46<=3,10,IF(C46<=6,30,IF(C46<=10,55,IF(C46<=20,80,100))))) | F46: 0.3 | G46: =IF(E46="","",E46*F46) | H46: Cada plataforma puede requerir accesos, proveedor, contrato, seguridad, conservación y transferencia.
A47: Proveedores con acceso a datos | B47: TI, cloud, marketing, logística, RR. HH., soporte, archivo, call center, seguridad y otros. | D47: proveedores | E47: =IF(C47="","",IF(C47<=5,10,IF(C47<=10,30,IF(C47<=20,55,IF(C47<=50,80,100))))) | F47: 0.25 | G47: =IF(E47="","",E47*F47) | H47: Aumenta revisión contractual, encargos, due diligence y transferencias.
A48: Canales de recolección | B48: Local físico, web, e-commerce, WhatsApp, redes, call center, app, formularios y otros. | D48: canales | E48: =IF(C48="","",IF(C48<=2,10,IF(C48<=4,30,IF(C48<=6,55,IF(C48<=9,80,100))))) | F48: 0.15 | G48: =IF(E48="","",E48*F48) | H48: Más canales implican más puntos de información, captura, trazabilidad y riesgo.
A49: Cloud / proveedores fuera de Ecuador | B49: ¿Usa proveedores tecnológicos o soporte cuya infraestructura o entidad está fuera de Ecuador? | D49: Sí / No / No sabe | E49: =IF(C49="","",IF(C49="Sí",100,IF(C49="No",0,60))) | F49: 0.15 | G49: =IF(E49="","",E49*F49) | H49: Puede requerir análisis de transferencias/comunicaciones internacionales.
A50: Gestión de datos por sucursales | B50: ¿La gestión de datos y archivos está centralizada o cada local opera con autonomía? | D50: seleccionar | E50: =IF(C50="","",IF(C50="Centralizada",0,IF(C50="Mixta",50,IF(C50="Descentralizada",100,75)))) | F50: 0.1 | G50: =IF(E50="","",E50*F50) | H50: La descentralización aumenta variaciones, accesos, archivos y entrevistas.
A51: Archivo físico | B51: ¿Mantiene formularios, facturas, expedientes, contratos o archivos con datos personales en papel? | D51: Sí / No / No sabe | E51: =IF(C51="","",IF(C51="Sí",100,IF(C51="No",0,60))) | F51: 0.05 | G51: =IF(E51="","",E51*F51) | H51: Añade controles físicos, conservación y eliminación.
A53: D. Madurez y documentación existente
A54: Variable | B54: Qué debe informar la empresa | C54: Respuesta / dato | D54: Unidad / opciones | E54: Score | F54: Peso interno | G54: Aporte | H54: Impacto en el alcance
A55: Registro de Actividades de Tratamiento (RAT) | B55: ¿Existe y está actualizado un RAT o inventario equivalente de tratamientos? | D55: Sí / Parcial / No / No sabe | E55: =IF(C55="","",IF(C55="Sí",0,IF(C55="Parcial",50,IF(C55="No",100,75)))) | F55: 0.14285714 | G55: =IF(E55="","",E55*F55) | H55: Si no existe, aumenta el esfuerzo de levantamiento y documentación.
A56: Política / avisos de privacidad | B56: ¿Existen políticas y avisos adaptados a los principales titulares y canales? | D56: Sí / Parcial / No / No sabe | E56: =IF(C56="","",IF(C56="Sí",0,IF(C56="Parcial",50,IF(C56="No",100,75)))) | F56: 0.14285714 | G56: =IF(E56="","",E56*F56) | H56: Determina trabajo de creación o revisión documental.
A57: Procedimiento de derechos | B57: ¿Existe un procedimiento documentado para atender derechos de titulares? | D57: Sí / Parcial / No / No sabe | E57: =IF(C57="","",IF(C57="Sí",0,IF(C57="Parcial",50,IF(C57="No",100,75)))) | F57: 0.14285714 | G57: =IF(E57="","",E57*F57) | H57: Afecta documentación, roles, plazos y evidencias.
A58: Procedimiento de incidentes | B58: ¿Existe un procedimiento para detectar, escalar, evaluar y documentar vulneraciones? | D58: Sí / Parcial / No / No sabe | E58: =IF(C58="","",IF(C58="Sí",0,IF(C58="Parcial",50,IF(C58="No",100,75)))) | F58: 0.14285714 | G58: =IF(E58="","",E58*F58) | H58: Aumenta trabajo de diseño y coordinación con seguridad/TI si no existe.
A59: Contratos con encargados / cláusulas | B59: ¿Los principales proveedores con acceso a datos tienen cláusulas o acuerdos adecuados? | D59: Sí / Parcial / No / No sabe | E59: =IF(C59="","",IF(C59="Sí",0,IF(C59="Parcial",50,IF(C59="No",100,75)))) | F59: 0.14285714 | G59: =IF(E59="","",E59*F59) | H59: Puede implicar revisión de múltiples contratos y proveedores.
A60: Conservación y eliminación | B60: ¿Existen reglas documentadas de retención, archivo, bloqueo o eliminación? | D60: Sí / Parcial / No / No sabe | E60: =IF(C60="","",IF(C60="Sí",0,IF(C60="Parcial",50,IF(C60="No",100,75)))) | F60: 0.14285714 | G60: =IF(E60="","",E60*F60) | H60: Si no existe, se debe levantar obligaciones y diseñar reglas por categorías.
A61: Seguridad y accesos documentados | B61: ¿Existen políticas/procedimientos para usuarios, accesos, contraseñas, respaldo, cifrado o proveedores? | D61: Sí / Parcial / No / No sabe | E61: =IF(C61="","",IF(C61="Sí",0,IF(C61="Parcial",50,IF(C61="No",100,75)))) | F61: 0.14285714 | G61: =IF(E61="","",E61*F61) | H61: Indica cuánto trabajo de control y evidencia será necesario.
A63: Resumen de complejidad del proyecto
A64: Dimensión | B64: Score 0-100 | C64: Peso global | D64: Contribución | E64: Interpretación y alcance sugerido
A65: Escala y volumen | B65: =IF(OR(B4<0.6,COUNT(C25:C30)=0),"",E20*30%+E31*70%) | C65: 0.2 | D65: =IF(B65="","",B65*C65) | E65: 0–25 | F65: Baja | G65: Assessment + implementación base | H65: Organización acotada, pocos procesos/sistemas o alta documentación existente.
A66: Procesos y estructura | B66: =IF(OR(B4<0.6,COUNT(C25:C30)=0),"",E21*20%+E22*25%+E23*35%+E24*20%) | C66: 0.25 | D66: =IF(B66="","",B66*C66) | E66: 26–50 | F66: Media | G66: Proyecto estándar | H66: Requiere levantamiento transversal, revisión de proveedores y documentación de controles.
A67: Sensibilidad y riesgo | B67: =IF(OR(B4<0.6,COUNT(C25:C30)=0),"",SUM(G35:G42)) | C67: 0.25 | D67: =IF(B67="","",B67*C67) | E67: 51–75 | F67: Alta | G67: Proyecto ampliado | H67: Mayor volumen, sucursales, tratamientos de riesgo o brechas relevantes.
A68: Tecnología y terceros | B68: =IF(OR(B4<0.6,COUNT(C25:C30)=0),"",SUM(G46:G51)) | C68: 0.15 | D68: =IF(B68="","",B68*C68) | E68: 76–100 | F68: Muy alta | G68: Proyecto complejo / por fases | H68: Conviene dividir diagnóstico, remediación prioritaria e implementación por oleadas.
A69: Brecha de madurez | B69: =IF(OR(B4<0.6,COUNT(C25:C30)=0),"",SUM(G55:G61)) | C69: 0.15 | D69: =IF(B69="","",B69*C69) | E69: Cobertura < 60% | F69: Información insuficiente | G69: No cotizar aún | H69: Solicitar datos adicionales antes de comprometer alcance, duración o presupuesto.
A70: Índice global de complejidad | B70: =IF(OR(B4<0.6,COUNT(C25:C30)=0),"",SUM(D65:D69)) | C70: 1 | D70: =IF(B70="","",B70) | E70: Nota | F70: Uso interno SMARTCIDI | G70: Heurística comercial | H70: No constituye requisito de la LOPDP ni una certificación de cumplimiento.
A72: * El presupuesto se calcula únicamente cuando SMARTCIDI ingresa una tarifa/hora. La estimación corresponde a diagnóstico + implementación base según el alcance resultante; no incluye IVA, software, viáticos, servicios jurídicos especializados, auditorías técnicas de terceros ni un servicio recurrente de DPD/acompañamiento posterior, salvo que se incorporen expresamente en la propuesta.

Sheet Dimensionamiento Servicios
A1: Dimensionamiento SMARTCIDI v1.3 – Implementación LOPDP, Auditoría y DPO | N1: ID | O1: Respuesta derivada | P1: Score | Q1: Peso IMP | R1: Aporte IMP | S1: Peso AUD | T1: Aporte AUD | U1: Peso DPO | V1: Aporte DPO
A2: Ficha cerrada de preventa para empresas del sector comercio. Responda rangos y marque Sí/No/No sabe por cada opción; el modelo calcula esfuerzo, duración y presupuesto. | N2: D01 | O2: =IF(C17="","",C17) -> 11–50 | P2: =IF(O2="","",IFERROR(VLOOKUP(N2&"|"&O2,'Parámetros SMARTCIDI'!$A$48:$D$163,4,FALSE),"")) -> 1 | Q2: 2 | R2: =IF(P2="","",P2*Q2) -> 2 | S2: 2 | T2: =IF(P2="","",P2*S2) -> 2 | U2: 3 | V2: =IF(P2="","",P2*U2) -> 3
N3: D02 | O3: =IF(C18="","",C18) -> 2–3 | P3: =IF(O3="","",IFERROR(VLOOKUP(N3&"|"&O3,'Parámetros SMARTCIDI'!$A$48:$D$163,4,FALSE),"")) -> 1 | Q3: 3 | R3: =IF(P3="","",P3*Q3) -> 3 | S3: 3 | T3: =IF(P3="","",P3*S3) -> 3 | U3: 2 | V3: =IF(P3="","",P3*U3) -> 2
A4: SALIDA COMERCIAL AUTOMÁTICA | N4: D03 | O4: =IF(C19="","",C19) -> 4–6 | P4: =IF(O4="","",IFERROR(VLOOKUP(N4&"|"&O4,'Parámetros SMARTCIDI'!$A$48:$D$163,4,FALSE),"")) -> 1 | Q4: 4 | R4: =IF(P4="","",P4*Q4) -> 4 | S4: 4 | T4: =IF(P4="","",P4*S4) -> 4 | U4: 4 | V4: =IF(P4="","",P4*U4) -> 4
A5: Servicio | B5: Índice | C5: Nivel | D5: Esfuerzo | E5: Duración | F5: Presupuesto objetivo sin IVA | G5: Banda comercial sin IVA | H5: Presupuesto / fee con IVA | I5: Valor 12 meses | J5: Equipo sugerido | K5: Estado | L5: Alerta / alcance | N5: D04 | O5: =IF(C20="","",C20) -> 1–5 | P5: =IF(O5="","",IFERROR(VLOOKUP(N5&"|"&O5,'Parámetros SMARTCIDI'!$A$48:$D$163,4,FALSE),"")) -> 0 | Q5: 5 | R5: =IF(P5="","",P5*Q5) -> 0 | S5: 5 | T5: =IF(P5="","",P5*S5) -> 0 | U5: 5 | V5: =IF(P5="","",P5*U5) -> 0
A6: Implementación LOPDP | B6: =IF($B$10=0,"",IFERROR(MIN(100,SUM(R2:R21)/(4*SUMIF(O2:O21,"<>",Q2:Q21))*100+IF(OR(C145="Sí",C146="Sí"),8,0)),"")) -> 68.211268 | C6: =IF(B6="","",IF(B6<=20,1,IF(B6<=40,2,IF(B6<=60,3,IF(B6<=80,4,5))))) -> 4 | D6: =IF(C6="","",VLOOKUP(C6,'Parámetros SMARTCIDI'!$A$15:$I$19,4,FALSE)&"–"&VLOOKUP(C6,'Parámetros SMARTCIDI'!$A$15:$I$19,5,FALSE)&" h") -> 140–200 h | E6: =IF(C6="","",ROUNDUP(VLOOKUP(C6,'Parámetros SMARTCIDI'!$A$15:$I$19,6,FALSE)*IF(O19="",1,VLOOKUP(O19,'Parámetros SMARTCIDI'!$A$39:$C$44,3,FALSE)),0)&"–"&ROUNDUP(VLOOKUP(C6,'Parámetros SMARTCIDI'!$A$15:$I$19,7,FALSE)*IF(O19="",1,VLOOKUP(O19,'Parámetros SMARTCIDI'!$A$39:$C$44,3,FALSE)),0)&" semanas") -> 24–36 semanas | F6: =IF(C6="","",MAX(VLOOKUP(C6,'Parámetros SMARTCIDI'!$A$15:$I$19,8,FALSE),MIN(((VLOOKUP(C6,'Parámetros SMARTCIDI'!$A$15:$I$19,4,FALSE)+VLOOKUP(C6,'Parámetros SMARTCIDI'!$A$15:$I$19,5,FALSE))/2)*'Parámetros SMARTCIDI'!$B$5*(1+'Parámetros SMARTCIDI'!$B$8),VLOOKUP(C6,'Parámetros SMARTCIDI'!$A$15:$I$19,9,FALSE)))) -> 10285 | G6: =IF(C6="","","USD "&TEXT(VLOOKUP(C6,'Parámetros SMARTCIDI'!$A$15:$I$19,8,FALSE),"#,##0")&"–"&TEXT(VLOOKUP(C6,'Parámetros SMARTCIDI'!$A$15:$I$19,9,FALSE),"#,##0")) -> USD 7000,0–11000,0 | H6: =IF(F6="","",F6*(1+'Parámetros SMARTCIDI'!$B$11)) -> 11622.05 | I6: — | J6: =IF(C6="","",IF(C6=1,"Consultor PDP",IF(C6=2,"Consultor + apoyo",IF(C6=3,"Líder PDP + seguridad",IF(C6=4,"Equipo multidisciplinario","Proyecto por frentes"))))) -> Equipo multidisciplinario | K6: =$F$10 -> PROVISIONAL – ≥3 incertidumbres | L6: =IF(OR(C145="Sí",C146="Sí"),"Validar alcance reforzado de ciberseguridad 2026; el modelo añade 8 puntos al índice.","Baseline LOPDP + controles de seguridad basados en riesgo.") -> Validar alcance reforzado de ciberseguridad 2026; el modelo añade 8 puntos al índice. | N6: D05 | O6: =IF(C21="","",C21) -> 61–80% | P6: =IF(O6="","",IFERROR(VLOOKUP(N6&"|"&O6,'Parámetros SMARTCIDI'!$A$48:$D$163,4,FALSE),"")) -> 1 | Q6: 5 | R6: =IF(P6="","",P6*Q6) -> 5 | S6: 4 | T6: =IF(P6="","",P6*S6) -> 4 | U6: 3 | V6: =IF(P6="","",P6*U6) -> 3
A7: Auditoría LOPDP | B7: =IF($B$10=0,"",IFERROR(MIN(100,SUM(T2:T21)/(4*SUMIF(O2:O21,"<>",S2:S21))*100+IF(OR(C145="Sí",C146="Sí"),8,0)),"")) -> 67.459459 | C7: =IF(B7="","",IF(B7<=20,1,IF(B7<=40,2,IF(B7<=60,3,IF(B7<=80,4,5))))) -> 4 | D7: =IF(C7="","",VLOOKUP(C7,'Parámetros SMARTCIDI'!$A$23:$I$27,4,FALSE)&"–"&VLOOKUP(C7,'Parámetros SMARTCIDI'!$A$23:$I$27,5,FALSE)&" h") -> 55–80 h | E7: =IF(C7="","",ROUNDUP(VLOOKUP(C7,'Parámetros SMARTCIDI'!$A$23:$I$27,6,FALSE)*IF(O19="",1,VLOOKUP(O19,'Parámetros SMARTCIDI'!$A$39:$C$44,3,FALSE)),0)&"–"&ROUNDUP(VLOOKUP(C7,'Parámetros SMARTCIDI'!$A$23:$I$27,7,FALSE)*IF(O19="",1,VLOOKUP(O19,'Parámetros SMARTCIDI'!$A$39:$C$44,3,FALSE)),0)&" semanas") -> 8–11 semanas | F7: =IF(C7="","",MAX(VLOOKUP(C7,'Parámetros SMARTCIDI'!$A$23:$I$27,8,FALSE),MIN(((VLOOKUP(C7,'Parámetros SMARTCIDI'!$A$23:$I$27,4,FALSE)+VLOOKUP(C7,'Parámetros SMARTCIDI'!$A$23:$I$27,5,FALSE))/2)*'Parámetros SMARTCIDI'!$B$6*(1+'Parámetros SMARTCIDI'!$B$9),VLOOKUP(C7,'Parámetros SMARTCIDI'!$A$23:$I$27,9,FALSE)))) -> 4252.5 | G7: =IF(C7="","","USD "&TEXT(VLOOKUP(C7,'Parámetros SMARTCIDI'!$A$23:$I$27,8,FALSE),"#,##0")&"–"&TEXT(VLOOKUP(C7,'Parámetros SMARTCIDI'!$A$23:$I$27,9,FALSE),"#,##0")) -> USD 3000,0–4500,0 | H7: =IF(F7="","",F7*(1+'Parámetros SMARTCIDI'!$B$11)) -> 4805.325 | I7: — | J7: =IF(C7="","",IF(C7=1,"Auditor PDP",IF(C7=2,"Auditor + apoyo",IF(C7=3,"Auditor + especialista TI",IF(C7=4,"Equipo auditor multidisciplinario","Auditoría por frentes"))))) -> Equipo auditor multidisciplinario | K7: =$F$10 -> PROVISIONAL – ≥3 incertidumbres | L7: =IF(OR(C145="Sí",C146="Sí"),"Incluir revisión específica de obligaciones/ciberseguridad. Pentest no incluido.","Auditoría LOPDP + organizativa/técnica; pentest/certificación se cotizan aparte.") -> Incluir revisión específica de obligaciones/ciberseguridad. Pentest no incluido. | N7: D06 | O7: =IF(C22="","",C22) -> 50.001–250.000 | P7: =IF(O7="","",IFERROR(VLOOKUP(N7&"|"&O7,'Parámetros SMARTCIDI'!$A$48:$D$163,4,FALSE),"")) -> 3 | Q7: 4 | R7: =IF(P7="","",P7*Q7) -> 12 | S7: 4 | T7: =IF(P7="","",P7*S7) -> 12 | U7: 5 | V7: =IF(P7="","",P7*U7) -> 15
A8: DPO externo | B8: =IF($B$10=0,"",IFERROR(SUM(V2:V21)/(4*SUMIF(O2:O21,"<>",U2:U21))*100,"")) -> 61.397059 | C8: =IF(B8="","",MAX(IF(B8<=20,1,IF(B8<=40,2,IF(B8<=60,3,IF(B8<=80,4,5)))),IF(COUNTIF(C135:C144,"Sí")>0,2,1),IF(AND(COUNTIF(C135:C144,"Sí")>0,P12>=2),3,1))) -> 4 | D8: =IF(C8="","",VLOOKUP(C8,'Parámetros SMARTCIDI'!$A$31:$I$35,4,FALSE)&" h/mes") -> 16 h/mes | E8: 12 meses | F8: =IF(C8="","",MAX(VLOOKUP(C8,'Parámetros SMARTCIDI'!$A$31:$I$35,5,FALSE),MIN(VLOOKUP(C8,'Parámetros SMARTCIDI'!$A$31:$I$35,4,FALSE)*'Parámetros SMARTCIDI'!$B$7,VLOOKUP(C8,'Parámetros SMARTCIDI'!$A$31:$I$35,6,FALSE)))) -> 1040 | G8: =IF(C8="","","USD "&TEXT(VLOOKUP(C8,'Parámetros SMARTCIDI'!$A$31:$I$35,5,FALSE),"#,##0")&"–"&TEXT(VLOOKUP(C8,'Parámetros SMARTCIDI'!$A$31:$I$35,6,FALSE),"#,##0")&" / mes") -> USD 850,0–1200,0 / mes | H8: =IF(F8="","",F8*(1+'Parámetros SMARTCIDI'!$B$11)) -> 1175.2 | I8: =IF(H8="","",H8*12) -> 14102.4 | J8: =IF(C8="","",VLOOKUP(C8,'Parámetros SMARTCIDI'!$A$31:$I$35,7,FALSE)) -> DPO senior + soporte | K8: =$F$10 -> PROVISIONAL – ≥3 incertidumbres | L8: =IF(COUNTIF(C135:C144,"Sí")>0,"Existe al menos un supuesto del Reglamento DPD que requiere validación jurídica prioritaria.",IF(OR(P12>=2,AND(P13>=2,P7>=3)),"Analizar obligación por categorías especiales, escala o monitoreo sistemático.","No se identifica disparador directo con la información declarada.")) -> Existe al menos un supuesto del Reglamento DPD que requiere validación jurídica prioritaria. | N8: D07 | O8: =IF(COUNTA(B32:B44)=0,"",IF(COUNTA(B32:B44)<13,"Desconocido",IF(B45<=2,"0–2",IF(B45<=5,"3–5",IF(B45<=8,"6–8",IF(B45<=11,"9–11","≥12")))))) -> 9–11 | P8: =IF(O8="","",IFERROR(VLOOKUP(N8&"|"&O8,'Parámetros SMARTCIDI'!$A$48:$D$163,4,FALSE),"")) -> 3 | Q8: 4 | R8: =IF(P8="","",P8*Q8) -> 12 | S8: 5 | T8: =IF(P8="","",P8*S8) -> 15 | U8: 4 | V8: =IF(P8="","",P8*U8) -> 12
N9: D08 | O9: =IF(COUNTA(B49:B60)=0,"",IF(COUNTA(B49:B60)<12,"Desconocido",IF(B61<=2,"0–2",IF(B61<=4,"3–4",IF(B61<=6,"5–6",IF(B61<=9,"7–9","≥10")))))) -> 7–9 | P9: =IF(O9="","",IFERROR(VLOOKUP(N9&"|"&O9,'Parámetros SMARTCIDI'!$A$48:$D$163,4,FALSE),"")) -> 3 | Q9: 3 | R9: =IF(P9="","",P9*Q9) -> 9 | S9: 3 | T9: =IF(P9="","",P9*S9) -> 9 | U9: 3 | V9: =IF(P9="","",P9*U9) -> 9
A10: Cobertura | B10: =((COUNTIF(C17:C28,"<>")/12)+(COUNTIF(B32:B44,"<>")/13)+(COUNTIF(B49:B60,"<>")/12)+(COUNTIF(B65:B76,"<>")/12)+(COUNTIF(C65:C76,"<>")/12)+(COUNTIF(B81:B92,"<>")/12)+(COUNTIF(B97:B102,"<>")/6)+(COUNTIF(B107:B116,"<>")/10)+(COUNTIF(B121:B130,"<>")/10))/9 -> 0.87962963 | C10: No sabe / desconocidos | D10: =COUNTIF(C17:C28,"Desconocido")+COUNTIF(C17:C28,"No sabe")+COUNTIF(B32:B44,"No sabe")+COUNTIF(B49:B60,"No sabe")+COUNTIF(B65:B76,"No sabe")+COUNTIF(C65:C76,"No sabe")+COUNTIF(B81:B92,"No sabe")+COUNTIF(B97:B102,"No sabe")+COUNTIF(B107:B116,"No sabe")+COUNTIF(B121:B130,"No sabe") -> 28 | E10: Estado información | F10: =IF(B10<'Parámetros SMARTCIDI'!$B$10,"PROVISIONAL – falta información",IF(D10>=3,"PROVISIONAL – ≥3 incertidumbres","RESULTADO UTILIZABLE")) -> PROVISIONAL – ≥3 incertidumbres | G10: IVA ref. | H10: ='Parámetros SMARTCIDI'!$B$11 -> 0.13 | I10: Modelo | J10: MD-SGPDP v1.3 | K10: Uso | L10: Interno SMARTCIDI | N10: D09 | O10: =IF(COUNTA(B65:B76)=0,"",IF(COUNTA(B65:B76)<12,"Desconocido",IF(B77<=2,"0–2",IF(B77<=4,"3–4",IF(B77<=7,"5–7",IF(B77<=10,"8–10","≥11")))))) -> 5–7 | P10: =IF(O10="","",IFERROR(VLOOKUP(N10&"|"&O10,'Parámetros SMARTCIDI'!$A$48:$D$163,4,FALSE),"")) -> 2 | Q10: 3 | R10: =IF(P10="","",P10*Q10) -> 6 | S10: 4 | T10: =IF(P10="","",P10*S10) -> 8 | U10: 3 | V10: =IF(P10="","",P10*U10) -> 6
N11: D10 | O11: =IF(COUNTA(C65:C76)=0,"",IF(COUNTA(C65:C76)<12,"Desconocido",IF(C77=0,"0",IF(C77=1,"1",IF(C77<=3,"2–3",IF(C77<=5,"4–5","≥6")))))) | P11: =IF(O11="","",IFERROR(VLOOKUP(N11&"|"&O11,'Parámetros SMARTCIDI'!$A$48:$D$163,4,FALSE),"")) | Q11: 3 | R11: =IF(P11="","",P11*Q11) | S11: 4 | T11: =IF(P11="","",P11*S11) | U11: 3 | V11: =IF(P11="","",P11*U11)
A12: INSTRUCCIONES DE USO | N12: D11 | O12: =IF(COUNTA(B81:B92)=0,"",IF(COUNTA(B81:B92)<12,"Desconocido",IF(B93=0,"0",IF(B93=1,"1",IF(B93=2,"2",IF(B93=3,"3","≥4")))))) -> Desconocido | P12: =IF(O12="","",IFERROR(VLOOKUP(N12&"|"&O12,'Parámetros SMARTCIDI'!$A$48:$D$163,4,FALSE),"")) -> 4 | Q12: 5 | R12: =IF(P12="","",P12*Q12) -> 20 | S12: 5 | T12: =IF(P12="","",P12*S12) -> 20 | U12: 5 | V12: =IF(P12="","",P12*U12) -> 20
A13: En las listas múltiples NO escriba un número ni nombres de herramientas en una sola celda. Marque cada categoría por separado. Si desconoce una respuesta, seleccione “No sabe” o “Desconocido”; tres o más incertidumbres relevantes generan una cotización provisional. | N13: D12 | O13: =IF(C23="","",C23) -> >10.000 | P13: =IF(O13="","",IFERROR(VLOOKUP(N13&"|"&O13,'Parámetros SMARTCIDI'!$A$48:$D$163,4,FALSE),"")) -> 4 | Q13: 4 | R13: =IF(P13="","",P13*Q13) -> 16 | S13: 4 | T13: =IF(P13="","",P13*S13) -> 16 | U13: 5 | V13: =IF(P13="","",P13*U13) -> 20
N14: D13 | O14: =IF(COUNTA(B97:B102)=0,"",IF(COUNTA(B97:B102)<6,"Desconocido",IF(B103=0,"0",IF(B103=1,"1",IF(B103=2,"2",IF(B103=3,"3","≥4")))))) -> 2 | P14: =IF(O14="","",IFERROR(VLOOKUP(N14&"|"&O14,'Parámetros SMARTCIDI'!$A$48:$D$163,4,FALSE),"")) -> 2 | Q14: 4 | R14: =IF(P14="","",P14*Q14) -> 8 | S14: 5 | T14: =IF(P14="","",P14*S14) -> 10 | U14: 5 | V14: =IF(P14="","",P14*U14) -> 10
A15: A. PERFIL, ESCALA Y MADUREZ DE PROCESOS | N15: D14 | O15: =IF(COUNTA(B107:B116)=0,"",IF(COUNTA(B107:B116)<10,"Desconocido",IF(B117>=9,"9–10",IF(B117>=7,"7–8",IF(B117>=5,"5–6",IF(B117>=3,"3–4","0–2")))))) -> 0–2 | P15: =IF(O15="","",IFERROR(VLOOKUP(N15&"|"&O15,'Parámetros SMARTCIDI'!$A$48:$D$163,4,FALSE),"")) -> 4 | Q15: 5 | R15: =IF(P15="","",P15*Q15) -> 20 | S15: 5 | T15: =IF(P15="","",P15*S15) -> 20 | U15: 3 | V15: =IF(P15="","",P15*U15) -> 12
A16: ID | B16: Pregunta cerrada | C16: Respuesta | D16: Opciones / unidad | E16: Criterio objetivo | N16: D15 | O16: =IF(COUNTA(B121:B130)=0,"",IF(COUNTA(B121:B130)<10,"Desconocido",IF(B131>=9,"9–10",IF(B131>=7,"7–8",IF(B131>=5,"5–6",IF(B131>=3,"3–4","0–2")))))) -> 0–2 | P16: =IF(O16="","",IFERROR(VLOOKUP(N16&"|"&O16,'Parámetros SMARTCIDI'!$A$48:$D$163,4,FALSE),"")) -> 4 | Q16: 5 | R16: =IF(P16="","",P16*Q16) -> 20 | S16: 4 | T16: =IF(P16="","",P16*S16) -> 16 | U16: 3 | V16: =IF(P16="","",P16*U16) -> 12
A17: D01 | B17: Número total de empleados y terceros recurrentes con acceso habitual a información. | C17: 11–50 | D17: rango | E17: Contar personas con acceso recurrente, no proveedores ocasionales. | N17: D16 | O17: =IF(C24="","",C24) -> Desconocido | P17: =IF(O17="","",IFERROR(VLOOKUP(N17&"|"&O17,'Parámetros SMARTCIDI'!$A$48:$D$163,4,FALSE),"")) -> 4 | Q17: 4 | R17: =IF(P17="","",P17*Q17) -> 16 | S17: 4 | T17: =IF(P17="","",P17*S17) -> 16 | U17: 4 | V17: =IF(P17="","",P17*U17) -> 16
A18: D02 | B18: Número total de sucursales, locales, oficinas, bodegas o centros con operación propia. | C18: 2–3 | D18: rango | E18: Contar ubicaciones con usuarios, archivos o procesos propios. | N18: D17 | O18: =IF(C25="","",C25) -> Desconocido | P18: =IF(O18="","",IFERROR(VLOOKUP(N18&"|"&O18,'Parámetros SMARTCIDI'!$A$48:$D$163,4,FALSE),"")) -> 4 | Q18: 3 | R18: =IF(P18="","",P18*Q18) -> 12 | S18: 3 | T18: =IF(P18="","",P18*S18) -> 12 | U18: 5 | V18: =IF(P18="","",P18*U18) -> 20
A19: D03 | B19: Número de áreas/unidades que tratan datos personales. | C19: 4–6 | D19: rango | E19: Área que recolecta, consulta, modifica, comparte o conserva datos. | N19: D18 | O19: =IF(C26="","",C26) -> Desconocido | P19: =IF(O19="","",IFERROR(VLOOKUP(N19&"|"&O19,'Parámetros SMARTCIDI'!$A$48:$D$163,4,FALSE),"")) -> 4 | Q19: 0 | R19: =IF(P19="","",P19*Q19) -> 0 | S19: 0 | T19: =IF(P19="","",P19*S19) -> 0 | U19: 0 | V19: =IF(P19="","",P19*U19) -> 0
A20: D04 | B20: Número de procesos de negocio que involucran datos personales. | C20: 1–5 | D20: rango | E20: Si no existe inventario, marcar Desconocido. | N20: D19 | O20: =IF(C27="","",C27) -> No sabe | P20: =IF(O20="","",IFERROR(VLOOKUP(N20&"|"&O20,'Parámetros SMARTCIDI'!$A$48:$D$163,4,FALSE),"")) -> 3 | Q20: 2 | R20: =IF(P20="","",P20*Q20) -> 6 | S20: 3 | T20: =IF(P20="","",P20*S20) -> 9 | U20: 1 | V20: =IF(P20="","",P20*U20) -> 3
A21: D05 | B21: Porcentaje de procesos anteriores formalmente identificados y documentados. | C21: 61–80% | D21: rango % | E21: Solo si existe ficha, flujo, procedimiento o equivalente vigente. | N21: D20 | O21: =IF(C28="","",C28) -> Centralizado | P21: =IF(O21="","",IFERROR(VLOOKUP(N21&"|"&O21,'Parámetros SMARTCIDI'!$A$48:$D$163,4,FALSE),"")) -> 0 | Q21: 3 | R21: =IF(P21="","",P21*Q21) -> 0 | S21: 3 | T21: =IF(P21="","",P21*S21) -> 0 | U21: 2 | V21: =IF(P21="","",P21*U21) -> 0
A22: D06 | B22: Número aproximado de titulares activos + históricos conservados. | C22: 50.001–250.000 | D22: rango | E22: Clientes, leads, empleados, ex empleados, proveedores persona natural y otros.
A23: D12 | B23: Número de registros de menores de 18 años tratados habitualmente. | C23: >10.000 | D23: rango | E23: No incluir interacciones meramente excepcionales.
A24: D16 | B24: Porcentaje de procesos con datos personales cubiertos por RAT/inventario equivalente. | C24: Desconocido | D24: rango % | E24: Cobertura real del RAT respecto de procesos.
A25: D17 | B25: Incidentes de privacidad o seguridad identificados en los últimos 24 meses. | C25: Desconocido | D25: rango | E25: Pérdida, phishing, malware, envío erróneo, acceso indebido, robo, fuga, etc.
A26: D18 | B26: Tiempo habitual para entregar evidencia solicitada por el consultor. | C26: Desconocido | D26: rango de días | E26: Afecta calendario, no horas técnicas.
A27: D19 | B27: ¿Mantiene archivo físico con datos personales? | C27: No sabe | D27: Sí / No / No sabe | E27: Contratos, formularios, expedientes, facturas, hojas de vida u otros.
A28: D20 | B28: ¿Cómo se gestiona la información entre sucursales/locales? | C28: Centralizado | D28: selección | E28: Centralizado = gobierno común; descentralizado = cada local gestiona archivos/usuarios con autonomía.
A30: B. SELECCIÓN MÚLTIPLE – marque cada categoría con Sí / No / No sabe
A31: Categoría de sistema | B31: ¿Se utiliza? | C31: Ejemplos | D31: Por qué importa
A32: ERP / gestión administrativa | B32: No | C32: SAP, Odoo, Dynamics, otros | D32: Inventario de sistemas, proveedor, accesos y conservación.
A33: POS / facturación / caja | B33: Sí | C33: POS, facturación electrónica, caja | D33: Datos de clientes, compras, facturas y medios de pago.
A34: CRM / gestión de clientes | B34: Sí | C34: HighLevel, HubSpot, Salesforce, otros | D34: Marketing, ventas, perfiles y comunicaciones.
A35: E-commerce / portal web | B35: No | C35: Shopify, WooCommerce, Magento, portal propio | D35: Clientes, pedidos, pagos, cookies y terceros.
A36: RR.HH. / nómina / asistencia | B36: Sí | C36: Nómina, IESS, asistencia, biometría | D36: Datos laborales y posibles categorías especiales.
A37: Nube / gestión documental | B37: Sí | C37: Google Workspace, Microsoft 365, Drive, Dropbox | D37: Ubicación, accesos, proveedores y transferencias.
A38: Correo / colaboración | B38: Sí | C38: Microsoft 365, Google Workspace, Slack, Teams | D38: Intercambio y conservación de información.
A39: Marketing / email / publicidad | B39: Sí | C39: Mailchimp, Meta Ads, Google Ads, automatización | D39: Prospección, segmentación, perfiles y oposición.
A40: WhatsApp / omnicanal / chat | B40: Sí | C40: WhatsApp Business, chat web, bots | D40: Canal de recolección, evidencia y terceros.
A41: CCTV / videovigilancia | B41: Sí | C41: DVR/NVR, cámaras cloud | D41: Imágenes, retención, accesos y señalización.
A42: Biometría / control de acceso | B42: Sí | C42: Huella, rostro, torniquetes | D42: Riesgo elevado cuando permite identificación única.
... A44: BI / analítica / data warehouse | B44: No | C44: Power BI, Tableau, BigQuery, otros | D44: Consolidación, cruces de datos y acceso ampliado.
A45: Resumen sistemas | B45: =COUNTIF(B32:B44,"Sí") -> 9 | C45: El modelo cuenta categorías marcadas “Sí”. | D45: No ingresar un total manual.
A47: C. CANALES DE RECOLECCIÓN – SELECCIÓN MÚLTIPLE
A48: Canal | B48: ¿Recolecta datos? | C48: Ejemplo de uso
A49: Local físico / POS | B49: Sí | C49: Compra, facturación, devolución.
A50: Formularios físicos | B50: No | C50: Registro, garantía, crédito, encuesta.
A51: Sitio web | B51: Sí | C51: Contacto, cookies, formularios.
A52: E-commerce | B52: No | C52: Cuenta, compra, entrega, pago.
A53: WhatsApp / mensajería | B53: Sí | C53: Ventas, servicio, soporte.
A54: Redes sociales | B54: Sí | C54: Leads, mensajes, campañas.
A55: Call center / teléfono | B55: No | C55: Ventas, reclamos, soporte.
A56: Aplicación móvil | B56: No | C56: Cuenta, geolocalización, fidelización.
A57: CRM / formularios comerciales | B57: No | C57: Lead, prospecto, oportunidad.
A58: Email / campañas | B58: Sí | C58: Boletines, promociones, remarketing.
A59: CCTV | B59: Sí | C59: Videovigilancia en local/bodega/oficina.
A60: Biometría / acceso | B60: Sí | C60: Asistencia, control de acceso.
A61: Resumen canales | B61: =COUNTIF(B49:B60,"Sí") -> 7 | C61: Categorías marcadas “Sí”.
A63: D. TERCEROS / PROVEEDORES – SELECCIÓN MÚLTIPLE
A64: Tipo de proveedor | B64: ¿Accede/procesa datos? | C64: ¿Entidad o infraestructura fuera de Ecuador? | D64: Ejemplos
A65: Cloud / hosting / SaaS | B65: No | D65: Microsoft, Google, AWS, CRM, e-commerce.
A66: Pasarela / adquirencia / pagos | B66: No | D66: Procesador de pagos, antifraude.
A67: Logística / delivery / courier | B67: No | D67: Direcciones, teléfono, pedidos.
A68: Marketing / publicidad / analytics | B68: Sí | D68: Agencias, email, pixel, analítica.
A69: RR.HH. / nómina / medicina ocupacional | B69: Sí | D69: Nómina, selección, beneficios.
A70: TI / soporte / ciberseguridad | B70: Sí | D70: Mesa de ayuda, backups, monitoreo.
A71: Seguridad / CCTV | B71: Sí | D71: Guardias, monitoreo, cámaras.
A72: Call center / atención al cliente | B72: No | D72: Outsourcing de contacto.
A73: Archivo / custodia / destrucción | B73: Sí | D73: Archivo físico, digitalización.
A74: Contable / legal / auditoría | B74: Sí | D74: Asesores con acceso a expedientes.
A75: ERP / CRM / software de negocio | B75: Sí | D75: Proveedores de aplicaciones.
A76: Otros outsourcing operativos | B76: No sabe | D76: Terceros con acceso recurrente.
A77: Resumen proveedores | B77: =COUNTIF(B65:B76,"Sí") -> 7 | C77: =COUNTIF(C65:C76,"Sí") -> 0 | D77: El modelo cuenta categorías, no contratos individuales.
A79: E. CATEGORÍAS ESPECIALES, SENSIBLES Y DATOS DE MAYOR IMPACTO – SELECCIÓN MÚLTIPLE
A80: Categoría | B80: ¿Se trata? | C80: Referencia práctica
A81: Etnia / origen racial | B81: Sí | C81: Dato sensible según definición LOPDP.
A82: Identidad de género o identidad cultural | B82: No | C82: Dato sensible según definición LOPDP.
A83: Religión / ideología / filiación política | B83: No | C83: Dato sensible según definición LOPDP.
A84: Pasado judicial | B84: No sabe | C84: Dato sensible según definición LOPDP.
A85: Condición migratoria / refugio | C85: Dato sensible o de especial vulnerabilidad según contexto.
A86: Orientación sexual / vida sexual | B86: No sabe | C86: Dato sensible.
A87: Datos de salud | B87: No | C87: Categoría especial; incluye salud física o mental.
A88: Datos biométricos para identificación única | B88: Sí | C88: Huella, rostro u otro patrón usado para identificar.
A89: Datos genéticos | B89: No sabe | C89: Dato sensible.
A90: Datos de niñas, niños o adolescentes | B90: Sí | C90: Categoría especial art. 25 LOPDP.
A91: Datos de discapacidad / sustitutos | B91: Sí | C91: Categoría especial art. 25 LOPDP.
A92: Datos crediticios / patrimoniales | B92: No sabe | C92: No siempre categoría especial, pero incrementa impacto y seguridad.
A93: Resumen categorías | B93: =COUNTIF(B81:B92,"Sí") -> 4 | C93: El índice D11 cuenta categorías marcadas “Sí”.
A95: F. MONITOREO / PERFILAMIENTO DE MAYOR IMPACTO – SELECCIÓN MÚLTIPLE
A96: Mecanismo | B96: ¿Se utiliza? | C96: Criterio
A97: CCTV / videovigilancia | B97: Sí | C97: Operación habitual de cámaras.
A98: Biometría para identificación/control | B98: Sí | C98: Huella, rostro u otro patrón.
A99: Geolocalización sistemática | B99: No | C99: Clientes, repartidores, flota o app.
A100: Perfilamiento / scoring | B100: No | C100: Preferencias, fraude, marketing, fidelización.
A101: Decisiones automatizadas con efecto relevante | B101: No | C101: Decisión sin intervención humana significativa.
A102: Tracking comportamental multicanal | B102: No | C102: Seguimiento de navegación/consumo entre canales.
A103: Resumen mecanismos | B103: =COUNTIF(B97:B102,"Sí") -> 2 | C103: Categorías marcadas “Sí”.
A105: G. CONTROLES BÁSICOS DE CIBERSEGURIDAD – MARQUE SOLO SI ESTÁ IMPLEMENTADO Y OPERATIVO
A106: Control | B106: ¿Implementado? | C106: Evidencia mínima esperada
A107: MFA en cuentas críticas | B107: No sabe | C107: Configuración / política / evidencia de activación.
...

Sheet Parámetros SMARTCIDI
A1: Parámetros internos SMARTCIDI – Motor de dimensionamiento v1.3
A2: Uso interno. Ajuste tarifas y bandas con experiencia real de SMARTCIDI. Las bandas no son tarifas oficiales ni determinaciones de la SPDP.
A4: Parámetro | B4: Valor inicial | C4: Unidad | D4: Criterio / fuente interna
A5: Tarifa implementación | B5: 55 | C5: USD/h | D5: Tarifa interna referencial SMARTCIDI; editable.
A6: Tarifa auditoría | B6: 60 | C6: USD/h | D6: Tarifa interna referencial SMARTCIDI; editable.
A7: Tarifa DPO senior | B7: 65 | C7: USD/h | D7: Tarifa interna referencial SMARTCIDI; editable.
A8: Contingencia implementación | B8: 0.1 | C8: % | D8: Coordinación, validaciones y hallazgos no previstos.
A9: Contingencia auditoría | B9: 0.05 | C9: % | D9: Coordinación y ampliación razonable de muestra.
A10: Cobertura mínima para resultado firme | B10: 0.85 | C10: % | D10: Por debajo de este umbral la cotización se marca provisional.
A11: IVA referencial | B11: 0.13 | C11: % | D11: Parámetro editable. Verificar tarifa vigente del servicio al emitir propuesta/factura.
A13: Calibración – IMPLEMENTACIÓN LOPDP + controles de seguridad asociados
A14: Nivel | B14: Índice mín. | C14: Índice máx. | D14: Horas mín. | E14: Horas máx. | F14: Semanas mín. | G14: Semanas máx. | H14: Banda mín. sin IVA | I14: Banda máx. sin IVA
A15: 1 | B15: 0 | C15: 20 | D15: 40 | E15: 55 | F15: 6 | G15: 8 | H15: 1800 | I15: 3000
A16: 2 | B16: 21 | C16: 40 | D16: 60 | E16: 85 | F16: 8 | G16: 12 | H16: 3000 | I16: 4500
A17: 3 | B17: 41 | C17: 60 | D17: 90 | E17: 130 | F17: 12 | G17: 16 | H17: 4500 | I17: 7000
A18: 4 | B18: 61 | C18: 80 | D18: 140 | E18: 200 | F18: 16 | G18: 24 | H18: 7000 | I18: 11000
A19: 5 | B19: 81 | C19: 100 | D19: 220 | E19: 320 | F19: 24 | G19: 36 | H19: 11000 | I19: 18000
A21: Calibración – AUDITORÍA LOPDP + revisión organizativa/técnica
A22: Nivel | B22: Índice mín. | C22: Índice máx. | D22: Horas mín. | E22: Horas máx. | F22: Semanas mín. | G22: Semanas máx. | H22: Banda mín. sin IVA | I22: Banda máx. sin IVA
A23: 1 | B23: 0 | C23: 20 | D23: 12 | E23: 18 | F23: 1 | G23: 2 | H23: 700 | I23: 1200
A24: 2 | B24: 21 | C24: 40 | D24: 20 | E24: 30 | F24: 2 | G24: 3 | H24: 1200 | I24: 1800
A25: 3 | B25: 41 | C25: 60 | D25: 35 | E25: 50 | F25: 3 | G25: 5 | H25: 1800 | I25: 3000
A26: 4 | B26: 61 | C26: 80 | D26: 55 | E26: 80 | F26: 5 | G26: 7 | H26: 3000 | I26: 4500
A27: 5 | B27: 81 | C27: 100 | D27: 90 | E27: 130 | F27: 6 | G27: 10 | H27: 4500 | I27: 7000
A29: Calibración – DPO EXTERNO (contrato 12 meses)
A30: Nivel | B30: Índice mín. | C30: Índice máx. | D30: Horas/mes | E30: Fee mín./mes | F30: Fee máx./mes | G30: Equipo sugerido | H30: Uso típico
A31: 1 | B31: 0 | C31: 20 | D31: 4 | E31: 250 | F31: 350 | G31: DPO externo | H31: Micro/pequeña, bajo volumen/riesgo
A32: 2 | B32: 21 | C32: 40 | D32: 6 | E32: 350 | F32: 500 | G32: DPO externo | H32: PyME estándar, varios procesos/sistemas
A33: 3 | B33: 41 | C33: 60 | D33: 10 | E33: 550 | F33: 750 | G33: DPO + apoyo especializado | H33: Mayor volumen, terceros o categorías especiales
A34: 4 | B34: 61 | C34: 80 | D34: 16 | E34: 850 | F34: 1200 | G34: DPO senior + soporte | H34: Alta exposición, múltiples procesos/sistemas
A35: 5 | B35: 81 | C35: 100 | D35: 24 | E35: 1250 | F35: 1800 | G35: DPO senior + equipo | H35: Dedicación intensiva / operación compleja
A38: Respuesta D18 | B38: Score | C38: Factor calendario
A39: ≤2 días | B39: 0 | C39: 1
A40: 3–5 días | B40: 1 | C40: 1.05
A41: 6–10 días | B41: 2 | C41: 1.15
A42: 11–20 días | B42: 3 | C42: 1.3
A43: >20 días | B43: 4 | C43: 1.5
A44: Desconocido | B44: 4 | C44: 1.5
A47: Clave | B47: ID | C47: Respuesta | D47: Score
A48: D01|1–10 | B48: D01 | C48: 1–10 | D48: 0
A49: D01|11–50 | B49: D01 | C49: 11–50 | D49: 1
A50: D01|51–200 | B50: D01 | C50: 51–200 | D50: 2
A51: D01|201–500 | B51: D01 | C51: 201–500 | D51: 3
A52: D01|>500 | B52: D01 | C52: >500 | D52: 4
A53: D01|Desconocido | B53: D01 | C53: Desconocido | D53: 4
A54: D02|1 | B54: D02 | C54: 1 | D54: 0
A55: D02|2–3 | B55: D02 | C55: 2–3 | D55: 1
A56: D02|4–10 | B56: D02 | C56: 4–10 | D56: 2
A57: D02|11–30 | B57: D02 | C57: 11–30 | D57: 3
A58: D02|>30 | B58: D02 | C58: >30 | D58: 4
A59: D02|Desconocido | B59: D02 | C59: Desconocido | D59: 4
... A163: D20|No sabe | B163: D20 | C163: No sabe | D163: 4
A166: Fuentes de calibración y marco de referencia – actualizar periódicamente
A167: Tipo | B167: Fuente | C167: URL | D167: Uso en el modelo
A168: Normativa | B168: Ley Orgánica de Protección de Datos Personales – Ecuador | C168: https://www.registroficial.gob.ec/ | D168: Seguridad, categorías especiales, responsabilidad proactiva y obligaciones generales.
A169: Normativa | B169: Reglamento del DPD – Resolución SPDP-SPD-2025-0028-R | C169: https://spdp.gob.ec/resolucion_028/ | D169: Compuertas de designación obligatoria del DPO/DPD y funciones.
A170: Normativa | B170: Ley Orgánica para el Fortalecimiento de la Ciberseguridad – R.O. 22/05/2026 | C170: https://www.registroficial.gob.ec/quinto-suplemento-no-290/ | D170: Compuerta de alcance reforzado para PSD, servicios esenciales e infraestructura crítica.
A171: Mercado | B171: Gruppo Avanti – Diagnóstico e Implementación LOPDP | C171: https://www.gruppoavanti.com/consultorias-it-iso/ | D171: Referencia pública: diagnóstico e implementación con precio/plazo publicado; no es tarifa oficial.
A172: Mercado | B172: Tempo Legal – Guía de precios DPD externo Ecuador 2026 | C172: https://tempolegal.com/delegado-de-proteccion-de-datos-externo-en-ecuador/ | D172: Referencia pública 2026 para fee DPD por tamaño/riesgo; no es tarifa oficial.
A173: Mercado | B173: Lexify Ecuador – planes legales / DPO | C173: https://lexify.ec/ | D173: Referencia pública adicional para servicios legales/datos.
A174: Tributario | B174: SRI – Impuesto al Valor Agregado | C174: https://www.sri.gob.ec/impuesto-al-valor-agregado-iva | D174: Referencia para verificar tarifa de IVA vigente al cotizar.
